Workbook

Sheet 00_Resumen
A1: Amelí · Sistema maestro del menú digital multilingüe
A2: Archivo preparado para menú QR mobile-first, traducciones, precios, ingeniería de menú, alérgenos, multimedia, SEO, canales y estadísticas.
A4: Indicador | B4: Resultado | D4: Flujo de trabajo recomendado
A5: Total de productos | B5: =COUNTA(02_Productos_MASTER!A5:A59) -> 55 | D5: 1 | E5: Validar nombres, descripciones y categorías | F5: 01_Menú_Multilingüe
A6: Productos activos | B6: =COUNTIF(02_Productos_MASTER!J5:J59,"Sí") -> 55 | D6: 2 | E6: Completar precios y costos | F6: 04_Precios
A7: Categorías | B7: =COUNTA(03_Categorías!A5:A17) -> 13 | D7: 3 | E7: Validar ingredientes y alérgenos | F7: 06_Ingredientes / 07_Alérgenos_Dietas
A8: Traducciones completas | B8: =COUNTIF(01_Menú_Multilingüe!N5:N59,"Completa") -> 55 | D8: 4 | E8: Cargar fotografías, enlaces y URL base | F8: 10_Multimedia_SEO / 13_Configuración
A9: Precios cargados | B9: =COUNT(04_Precios!D5:D59) -> 0 | D9: 5 | E9: Definir visibilidad y temporalidad | F9: 11_Canales_QR
A10: Fotografías cargadas | B10: =COUNTIF(10_Multimedia_SEO!C5:C59,"<>") -> 0 | D10: 6 | E10: Cargar ventas y medir interacción | F10: 12_Estadísticas
A11: Unidades vendidas registradas | B11: =SUM(12_Estadísticas!C5:C59) -> 0 | D11: 7 | E11: Tomar decisiones de ingeniería de menú | F11: 09_Ingeniería_Menú
A12: Productos clasificados | B12: =COUNTIF(09_Ingeniería_Menú!L5:L59,"Estrella")+COUNTIF(09_Ingeniería_Menú!L5:L59,"Caballo de batalla")+COUNTIF(09_Ingeniería_Menú!L5:L59,"Incógnita")+COUNTIF(09_Ingeniería_Menú!L5:L59,"Perro") -> 0
A15: Orden | B15: Categoría | C15: Productos | E15: Notas críticas antes de publicar
A16: 1 | B16: Desayunos & Meriendas | C16: =03_Categorías!M5 -> 4 | E16: • | F16: No tratar «Sin TACC» como garantía sin validar certificación y manipulación.
A17: 2 | B17: Delicias | C17: =03_Categorías!M6 -> 7 | E17: • | F17: No publicar alérgenos basados únicamente en el nombre del producto.
A18: 3 | B18: Té en Hebras | C18: =03_Categorías!M7 -> 1 | E18: • | F18: Mantener el QR físico permanente; controlar promociones y disponibilidad desde la web.
A19: 4 | B19: Tisanas | C19: =03_Categorías!M8 -> 3 | E19: • | F19: Las etiquetas «Más vendido» y la clasificación deben provenir de datos reales.
A20: 5 | B20: Blends | C20: =03_Categorías!M9 -> 4 | E20: • | F20: Revisar precios, disponibilidad y horarios antes de cada temporada turística.
A21: 6 | B21: Especiales | C21: =03_Categorías!M10 -> 2
A22: 7 | B22: Café Clásico | C22: =03_Categorías!M11 -> 7
A23: 8 | B23: Café Frío | C23: =03_Categorías!M12 -> 3
A24: 9 | B24: Batidos & Jugos | C24: =03_Categorías!M13 -> 6
A25: 10 | B25: Adicionales | C25: =03_Categorías!M14 -> 2
A26: 11 | B26: Sin TACC | C26: =03_Categorías!M15 -> 4
A27: 12 | B27: Tortas & Tartas | C27: =03_Categorías!M16 -> 7
A28: 13 | B28: Sándwiches & Tostones | C28: =03_Categorías!M17 -> 5
A31: CÓMO USAR ESTE ARCHIVO (guía rápida)
A32: Convención de colores | B32: Amarillo = lo cargás vos · Naranja = dice «Verificar»: confirmalo y elegí Sí/No · Sin color = se calcula solo.
A33: Para publicar el menú | B33: Solo necesitás tres hojas: 01 (nombres y textos), 02 (qué se muestra y en qué orden) y 04 (precios).
A34: 01_Menú_Multilingüe | B34: Los textos en 5 idiomas. Si editás, mirá que la columna «Estado de traducción» siga en «Completa».
A35: 02_Productos_MASTER | B35: El interruptor de cada producto: activo, destacado, recomendado, nuevo. Todo con desplegable Sí/No.
A36: 03_Categorías | B36: El orden y nombre de las secciones del menú. Casi nunca se toca.
A37: 04_Precios | B37: Cargá precio local y costo (amarillo). El resto (USD, margen, fecha) se calcula solo.
A38: 05 a 08 | B38: Ficha operativa, ingredientes, alérgenos y personalización. Andá reemplazando los «Verificar» con desplegables.
A39: 09_Ingeniería_Menú | B39: Se llena sola con precios (04) y ventas (12). Clasifica: Estrella / Caballo / Incógnita / Perro.
A40: 10 a 12 | B40: Fotos y SEO, canales de publicación y estadísticas. Para más adelante; no bloquean el menú.
A41: 13_Configuración | B41: Datos generales: tipo de cambio (amarillo), WhatsApp, Instagram, dirección.
A42: Ordenar y filtrar | B42: Podés ordenar o filtrar tranquilo: las fórmulas buscan por ID, no por posición de fila.

Sheet 01_Menú_Multilingüe
A1: Menú multilingüe · Amelí Casa de Té & Brunch
A2: Base editorial principal para el menú QR. Las traducciones están localizadas para turistas y preservan los nombres propios cuando aportan identidad.
A4: ID | B4: Categoría | C4: Orden | D4: Nombre ES-AR | E4: Nombre EN-UK | F4: Nombre PT-BR | G4: Nombre FR-FR | H4: Nombre IT-IT | I4: Descripción ES-AR | J4: Descripción EN-UK | K4: Descripción PT-BR | L4: Descripción FR-FR | M4: Descripción IT-IT | N4: Estado de traducción
A5: DYM001 | B5: Desayunos & Meriendas | C5: 1 | D5: Avocado | E5: Avocado Breakfast | F5: Café da manhã com abacate | G5: Petit-déjeuner à l’avocat | H5: Colazione con avocado | I5: Bowl de huevos revueltos y palta, acompañado de dos tostadas, queso crema, café o té y un vaso pequeño de jugo de naranja. | J5: A bowl of scrambled eggs and avocado, served with two slices of toast, cream cheese, coffee or tea, and a small glass of orange juice. | K5: Bowl de ovos mexidos com abacate, acompanhado de duas torradas, cream cheese, café ou chá e um pequeno copo de suco de laranja. | L5: Bol d’œufs brouillés et d’avocat, accompagné de deux toasts, de fromage frais, d’un café ou d’un thé et d’un petit verre de jus d’orange. | M5: Bowl con uova strapazzate e avocado, accompagnato da due fette di pane tostato, formaggio spalmabile, caffè o tè e un piccolo bicchiere di succo d’arancia. | N5: =IF(COUNTA(D5:M5)=10,"Completa","Revisar") -> Completa
A6: DYM002 | B6: Desayunos & Meriendas | C6: 2 | D6: Desayuno clásico | E6: Classic Breakfast | F6: Café da manhã clássico | G6: Petit-déjeuner classique | H6: Colazione classica | I6: Dos tostadas con queso crema y mermelada, acompañadas de café o té y un vaso pequeño de jugo de naranja. | J6: Two slices of toast with cream cheese and jam, served with coffee or tea and a small glass of orange juice. | K6: Duas torradas com cream cheese e geleia, acompanhadas de café ou chá e um pequeno copo de suco de laranja. | L6: Deux toasts avec fromage frais et confiture, accompagnés d’un café ou d’un thé et d’un petit verre de jus d’orange. | M6: Due fette di pane tostato con formaggio spalmabile e confettura, accompagnate da caffè o tè e da un piccolo bicchiere di succo d’arancia. | N6: =IF(COUNTA(D6:M6)=10,"Completa","Revisar") -> Completa
A7: DYM003 | B7: Desayunos & Meriendas | C7: 3 | D7: Desayuno mendocino | E7: Mendoza Breakfast | F7: Café da manhã mendocino | G7: Petit-déjeuner mendocin | H7: Colazione mendocina | I7: Dos raspaditas mendocinas, acompañadas de café o té y un vaso pequeño de jugo de naranja. | J7: Two traditional Mendoza raspaditas, served with coffee or tea and a small glass of orange juice. | K7: Duas raspaditas tradicionais de Mendoza, acompanhadas de café ou chá e um pequeno copo de suco de laranja. | L7: Deux raspaditas traditionnelles de Mendoza, accompagnées d’un café ou d’un thé et d’un petit verre de jus d’orange. | M7: Due raspaditas tradizionali di Mendoza, accompagnate da caffè o tè e da un piccolo bicchiere di succo d’arancia. | N7: =IF(COUNTA(D7:M7)=10,"Completa","Revisar") -> Completa
A8: DYM004 | B8: Desayunos & Meriendas | C8: 4 | D8: Desayuno saludable | E8: Healthy Breakfast | F8: Café da manhã saudável | G8: Petit-déjeuner équilibré | H8: Colazione salutare | I8: Yogur con frutas de estación, granola, frutos secos, miel y coco, acompañado de café o té y un vaso pequeño de jugo de naranja. | J8: Yoghurt with seasonal fruit, granola, nuts, honey and coconut, served with coffee or tea and a small glass of orange juice. | K8: Iogurte com frutas da estação, granola, castanhas, mel e coco, acompanhado de café ou chá e um pequeno copo de suco de laranja. | L8: Yaourt aux fruits de saison, granola, fruits à coque, miel et noix de coco, accompagné d’un café ou d’un thé et d’un petit verre de jus d’orange. | M8: Yogurt con frutta di stagione, granola, frutta secca, miele e cocco, accompagnato da caffè o tè e da un piccolo bicchiere di succo d’arancia. | N8: =IF(COUNTA(D8:M8)=10,"Completa","Revisar") -> Completa
A9: DEL001 | B9: Delicias | C9: 1 | D9: Bowl de huevos | E9: Egg Bowl | F9: Bowl de ovos | G9: Bowl d’œufs | H9: Bowl di uova | I9: Huevos preparados al momento y servidos en bowl. Consultar los acompañamientos disponibles. | J9: Eggs cooked to order and served in a bowl. Please ask about the available accompaniments. | K9: Ovos preparados na hora e servidos em bowl. Consulte os acompanhamentos disponíveis. | L9: Œufs préparés à la demande et servis dans un bol. Merci de consulter les accompagnements disponibles. | M9: Uova preparate al momento e servite in bowl. Chiedere quali accompagnamenti sono disponibili. | N9: =IF(COUNTA(D9:M9)=10,"Completa","Revisar") -> Completa
A10: DEL002 | B10: Delicias | C10: 2 | D10: Bowl de frutas | E10: Seasonal Fruit Bowl | F10: Bowl de frutas da estação | G10: Bol de fruits de saison | H10: Bowl di frutta di stagione | I10: Selección de frutas frescas de estación, servidas en bowl. | J10: A selection of fresh seasonal fruit, served in a bowl. | K10: Seleção de frutas frescas da estação, servidas em bowl. | L10: Sélection de fruits frais de saison, servis dans un bol. | M10: Selezione di frutta fresca di stagione, servita in bowl. | N10: =IF(COUNTA(D10:M10)=10,"Completa","Revisar") -> Completa
A11: DEL003 | B11: Delicias | C11: 3 | D11: Chipá | E11: Chipá Cheese Rolls | F11: Pão de queijo tipo chipá | G11: Petits pains au fromage chipá | H11: Panini al formaggio chipá | I11: Panecillos de almidón de mandioca y queso, suaves por dentro y ligeramente crocantes por fuera. | J11: Cheese rolls made with cassava starch, soft inside and lightly crisp outside. | K11: Pãezinhos de polvilho e queijo, macios por dentro e levemente crocantes por fora. | L11: Petits pains au fromage à base de fécule de manioc, moelleux à l’intérieur et légèrement croustillants à l’extérieur. | M11: Panini al formaggio preparati con amido di manioca, morbidi all’interno e leggermente croccanti fuori. | N11: =IF(COUNTA(D11:M11)=10,"Completa","Revisar") -> Completa
A12: DEL004 | B12: Delicias | C12: 4 | D12: Medialunas | E12: Argentine Croissants | F12: Medialunas argentinas | G12: Croissants argentins | H12: Cornetti argentini | I12: Medialunas argentinas suaves y hojaldradas. Consultar presentación y cantidad por porción. | J12: Soft, flaky Argentine croissants. Please ask about serving size and presentation. | K12: Medialunas argentinas macias e folhadas. Consulte a quantidade e a apresentação da porção. | L12: Croissants argentins moelleux et feuilletés. Merci de consulter la quantité et la présentation. | M12: Cornetti argentini soffici e sfogliati. Chiedere quantità e presentazione della porzione. | N12: =IF(COUNTA(D12:M12)=10,"Completa","Revisar") -> Completa
A13: DEL005 | B13: Delicias | C13: 5 | D13: Mini budines | E13: Mini Loaf Cakes | F13: Mini bolos tipo inglês | G13: Mini cakes | H13: Mini plumcake | I13: Selección de mini budines artesanales. Consultar los sabores disponibles del día. | J13: A selection of handmade mini loaf cakes. Please ask about today’s available flavours. | K13: Seleção de mini bolos artesanais. Consulte os sabores disponíveis do dia. | L13: Sélection de mini cakes artisanaux. Merci de demander les parfums disponibles du jour. | M13: Selezione di mini plumcake artigianali. Chiedere i gusti disponibili del giorno. | N13: =IF(COUNTA(D13:M13)=10,"Completa","Revisar") -> Completa
A14: DEL006 | B14: Delicias | C14: 6 | D14: Raspaditas mendocinas | E14: Mendoza Raspaditas | F14: Raspaditas mendocinas | G14: Raspaditas de Mendoza | H14: Raspaditas mendocine | I14: Tortitas saladas tradicionales de Mendoza, de textura firme, ideales para acompañar café, té o mate. | J14: Traditional savoury baked rounds from Mendoza, with a firm texture and perfect alongside coffee, tea or mate. | K14: Tortinhas salgadas tradicionais de Mendoza, de textura firme, ideais para acompanhar café, chá ou mate. | L14: Petites galettes salées traditionnelles de Mendoza, à la texture ferme, idéales avec un café, un thé ou du maté. | M14: Focaccine salate tradizionali di Mendoza, dalla consistenza compatta, ideali con caffè, tè o mate. | N14: =IF(COUNTA(D14:M14)=10,"Completa","Revisar") -> Completa
A15: DEL007 | B15: Delicias | C15: 7 | D15: Smoothie bowl | E15: Smoothie Bowl | F15: Smoothie bowl | G15: Smoothie bowl | H15: Smoothie bowl | I15: Base cremosa de frutas servida en bowl con toppings. Consultar la combinación disponible del día. | J15: A creamy fruit base served in a bowl with toppings. Please ask about today’s available combination. | K15: Base cremosa de frutas servida em bowl com toppings. Consulte a combinação disponível do dia. | L15: Base crémeuse de fruits servie dans un bol avec garnitures. Merci de demander la composition disponible du jour. | M15: Base cremosa di frutta servita in bowl con topping. Chiedere la combinazione disponibile del giorno. | N15: =IF(COUNTA(D15:M15)=10,"Completa","Revisar") -> Completa
A16: TEH001 | B16: Té en Hebras | C16: 1 | D16: Selección de té en hebras | E16: Loose-Leaf Tea Selection | F16: Seleção de chás de folhas soltas | G16: Sélection de thés en feuilles | H16: Selezione di tè in foglia | I16: Té negro, pu-erh o verde, preparado en hebras. | J16: Black, pu-erh or green tea, brewed from loose leaves. | K16: Chá preto, pu-erh ou verde, preparado com folhas soltas. | L16: Thé noir, pu-erh ou vert, préparé en feuilles. | M16: Tè nero, pu-erh o verde, preparato con foglie sfuse. | N16: =IF(COUNTA(D16:M16)=10,"Completa","Revisar") -> Completa
... A59: SAT005 | B59: Sándwiches & Tostones | C59: 5 | D59: Pistachero | E59: Pistachio Mortadella Sandwich | F59: Sanduíche de mortadela e pistache | G59: Sandwich mortadelle & pistache | H59: Panino mortadella & pistacchio | I59: Sándwich de mortadela, queso, manteca especiada, pistacho y queso gratinado. | J59: A sandwich with mortadella, cheese, spiced butter, pistachios and melted cheese. | K59: Sanduíche com mortadela, queijo, manteiga temperada, pistache e queijo gratinado. | L59: Sandwich à la mortadelle, au fromage, au beurre épicé, aux pistaches et au fromage gratiné. | M59: Panino con mortadella, formaggio, burro speziato, pistacchi e formaggio gratinato. | N59: =IF(COUNTA(D59:M59)=10,"Completa","Revisar") -> Completa

Sheet 02_Productos_MASTER
A1: Productos MASTER · Fuente única del menú
A2: Gobierna el orden, estado y señalización comercial de cada producto. «Más vendido» debe completarse únicamente con datos reales.
A4: ID | B4: SKU | C4: Grupo principal | D4: Categoría | E4: Código categoría | F4: Orden categoría | G4: Orden producto | H4: Orden global | I4: Página fuente | J4: Producto activo | K4: Destacado editorial | L4: Recomendado | M4: Más vendido | N4: Nuevo | O4: Edición limitada | P4: Etiqueta inicial | Q4: Observaciones
A5: DYM001 | B5: DYM001 | C5: Desayunos & Brunch | D5: Desayunos & Meriendas | E5: DYM | F5: 1 | G5: 1 | H5: =(F5*100)+G5 -> 101 | I5: 2 | J5: Sí | K5: Sí | L5: Sí | M5: No | N5: No | O5: No | P5: Recomendado Amelí
A6: DYM002 | B6: DYM002 | C6: Desayunos & Brunch | D6: Desayunos & Meriendas | E6: DYM | F6: 1 | G6: 2 | H6: =(F6*100)+G6 -> 102 | I6: 2 | J6: Sí | K6: No | L6: No | M6: No | N6: No | O6: No
A7: DYM003 | B7: DYM003 | C7: Desayunos & Brunch | D7: Desayunos & Meriendas | E7: DYM | F7: 1 | G7: 3 | H7: =(F7*100)+G7 -> 103 | I7: 2 | J7: Sí | K7: No | L7: Sí | M7: No | N7: No | O7: No | P7: Identidad mendocina
A8: DYM004 | B8: DYM004 | C8: Desayunos & Brunch | D8: Desayunos & Meriendas | E8: DYM | F8: 1 | G8: 4 | H8: =(F8*100)+G8 -> 104 | I8: 2 | J8: Sí | K8: No | L8: Sí | M8: No | N8: No | O8: No | P8: Opción equilibrada
A9: DEL001 | B9: DEL001 | C9: Desayunos & Brunch | D9: Delicias | E9: DEL | F9: 2 | G9: 1 | H9: =(F9*100)+G9 -> 201 | I9: 2 | J9: Sí | K9: No | L9: No | M9: No | N9: No | O9: No | Q9: Confirmar receta y acompañamientos.
A10: DEL002 | B10: DEL002 | C10: Desayunos & Brunch | D10: Delicias | E10: DEL | F10: 2 | G10: 2 | H10: =(F10*100)+G10 -> 202 | I10: 2 | J10: Sí | K10: No | L10: No | M10: No | N10: No | O10: No
A11: DEL003 | B11: DEL003 | C11: Desayunos & Brunch | D11: Delicias | E11: DEL | F11: 2 | G11: 3 | H11: =(F11*100)+G11 -> 203 | I11: 2 | J11: Sí | K11: No | L11: No | M11: No | N11: No | O11: No
A12: DEL004 | B12: DEL004 | C12: Desayunos & Brunch | D12: Delicias | E12: DEL | F12: 2 | G12: 4 | H12: =(F12*100)+G12 -> 204 | I12: 2 | J12: Sí | K12: No | L12: No | M12: No | N12: No | O12: No
A13: DEL005 | B13: DEL005 | C13: Desayunos & Brunch | D13: Delicias | E13: DEL | F13: 2 | G13: 5 | H13: =(F13*100)+G13 -> 205 | I13: 2 | J13: Sí | K13: No | L13: No | M13: No | N13: No | O13: No | Q13: Los ingredientes varían según el sabor.
A14: DEL006 | B14: DEL006 | C14: Desayunos & Brunch | D14: Delicias | E14: DEL | F14: 2 | G14: 6 | H14: =(F14*100)+G14 -> 206 | I14: 2 | J14: Sí | K14: No | L14: No | M14: No | N14: No | O14: No | P14: Especialidad regional
A15: DEL007 | B15: DEL007 | C15: Desayunos & Brunch | D15: Delicias | E15: DEL | F15: 2 | G15: 7 | H15: =(F15*100)+G15 -> 207 | I15: 2 | J15: Sí | K15: No | L15: No | M15: No | N15: No | O15: No | Q15: Confirmar ingredientes, toppings y base líquida.
A16: TEH001 | B16: TEH001 | C16: Té & Infusiones | D16: Té en Hebras | E16: TEH | F16: 3 | G16: 1 | H16: =(F16*100)+G16 -> 301 | I16: 2 | J16: Sí | K16: No | L16: No | M16: No | N16: No | O16: No
A17: TIS001 | B17: TIS001 | C17: Té & Infusiones | D17: Tisanas | E17: TIS | F17: 4 | G17: 1 | H17: =(F17*100)+G17 -> 401 | I17: 2 | J17: Sí | K17: No | L17: No | M17: No | N17: No | O17: No
A18: TIS002 | B18: TIS002 | C18: Té & Infusiones | D18: Tisanas | E18: TIS | F18: 4 | G18: 2 | H18: =(F18*100)+G18 -> 402 | I18: 2 | J18: Sí | K18: No | L18: No | M18: No | N18: No | O18: No
A19: TIS003 | B19: TIS003 | C19: Té & Infusiones | D19: Tisanas | E19: TIS | F19: 4 | G19: 3 | H19: =(F19*100)+G19 -> 403 | I19: 2 | J19: Sí | K19: No | L19: No | M19: No | N19: No | O19: No
A20: BLE001 | B20: BLE001 | C20: Té & Infusiones | D20: Blends | E20: BLE | F20: 5 | G20: 1 | H20: =(F20*100)+G20 -> 501 | I20: 2 | J20: Sí | K20: Sí | L20: Sí | M20: No | N20: No | O20: No | P20: Blend de la casa
A21: BLE002 | B21: BLE002 | C21: Té & Infusiones | D21: Blends | E21: BLE | F21: 5 | G21: 2 | H21: =(F21*100)+G21 -> 502 | I21: 2 | J21: Sí | K21: No | L21: No | M21: No | N21: No | O21: No
A22: BLE003 | B22: BLE003 | C22: Té & Infusiones | D22: Blends | E22: BLE | F22: 5 | G22: 3 | H22: =(F22*100)+G22 -> 503 | I22: 2 | J22: Sí | K22: No | L22: No | M22: No | N22: No | O22: No
A23: BLE004 | B23: BLE004 | C23: Té & Infusiones | D23: Blends | E23: BLE | F23: 5 | G23: 4 | H23: =(F23*100)+G23 -> 504 | I23: 2 | J23: Sí | K23: No | L23: No | M23: No | N23: No | O23: No
A24: ESP001 | B24: ESP001 | C24: Té & Infusiones | D24: Especiales | E24: ESP | F24: 6 | G24: 1 | H24: =(F24*100)+G24 -> 601 | I24: 2 | J24: Sí | K24: No | L24: No | M24: No | N24: No | O24: No
A25: ESP002 | B25: ESP002 | C25: Té & Infusiones | D25: Especiales | E25: ESP | F25: 6 | G25: 2 | H25: =(F25*100)+G25 -> 602 | I25: 2 | J25: Sí | K25: Sí | L25: Sí | M25: No | N25: No | O25: No | P25: Especialidad Amelí
A26: CCL001 | B26: CCL001 | C26: Cafetería | D26: Café Clásico | E26: CCL | F26: 7 | G26: 1 | H26: =(F26*100)+G26 -> 701 | I26: 3 | J26: Sí | K26: No | L26: No | M26: No | N26: No | O26: No
A27: CCL002 | B27: CCL002 | C27: Cafetería | D27: Café Clásico | E27: CCL | F27: 7 | G27: 2 | H27: =(F27*100)+G27 -> 702 | I27: 3 | J27: Sí | K27: No | L27: No | M27: No | N27: No | O27: No
A28: CCL003 | B28: CCL003 | C28: Cafetería | D28: Café Clásico | E28: CCL | F28: 7 | G28: 3 | H28: =(F28*100)+G28 -> 703 | I28: 3 | J28: Sí | K28: No | L28: No | M28: No | N28: No | O28: No
A29: CCL004 | B29: CCL004 | C29: Cafetería | D29: Café Clásico | E29: CCL | F29: 7 | G29: 4 | H29: =(F29*100)+G29 -> 704 | I29: 3 | J29: Sí | K29: No | L29: No | M29: No | N29: No | O29: No
A30: CCL005 | B30: CCL005 | C30: Cafetería | D30: Café Clásico | E30: CCL | F30: 7 | G30: 5 | H30: =(F30*100)+G30 -> 705 | I30: 3 | J30: Sí | K30: No | L30: No | M30: No | N30: No | O30: No
A31: CCL006 | B31: CCL006 | C31: Cafetería | D31: Café Clásico | E31: CCL | F31: 7 | G31: 6 | H31: =(F31*100)+G31 -> 706 | I31: 3 | J31: Sí | K31: No | L31: No | M31: No | N31: No | O31: No
A32: CCL007 | B32: CCL007 | C32: Cafetería | D32: Café Clásico | E32: CCL | F32: 7 | G32: 7 | H32: =(F32*100)+G32 -> 707 | I32: 3 | J32: Sí | K32: No | L32: Sí | M32: No | N32: No | O32: No
A33: CFR001 | B33: CFR001 | C33: Cafetería | D33: Café Frío | E33: CFR | F33: 8 | G33: 1 | H33: =(F33*100)+G33 -> 801 | I33: 3 | J33: Sí | K33: No | L33: No | M33: No | N33: No | O33: No
A34: CFR002 | B34: CFR002 | C34: Cafetería | D34: Café Frío | E34: CFR | F34: 8 | G34: 2 | H34: =(F34*100)+G34 -> 802 | I34: 3 | J34: Sí | K34: No | L34: No | M34: No | N34: No | O34: No
A35: CFR003 | B35: CFR003 | C35: Cafetería | D35: Café Frío | E35: CFR | F35: 8 | G35: 3 | H35: =(F35*100)+G35 -> 803 | I35: 3 | J35: Sí | K35: Sí | L35: Sí | M35: No | N35: No | O35: No | P35: Favorito dulce
A36: BYJ001 | B36: BYJ001 | C36: Bebidas Frías | D36: Batidos & Jugos | E36: BYJ | F36: 9 | G36: 1 | H36: =(F36*100)+G36 -> 901 | I36: 3 | J36: Sí | K36: No | L36: No | M36: No | N36: No | O36: No | Q36: Confirmar si la base contiene leche.
A37: BYJ002 | B37: BYJ002 | C37: Bebidas Frías | D37: Batidos & Jugos | E37: BYJ | F37: 9 | G37: 2 | H37: =(F37*100)+G37 -> 902 | I37: 3 | J37: Sí | K37: No | L37: No | M37: No | N37: No | O37: No
A38: BYJ003 | B38: BYJ003 | C38: Bebidas Frías | D38: Batidos & Jugos | E38: BYJ | F38: 9 | G38: 3 | H38: =(F38*100)+G38 -> 903 | I38: 3 | J38: Sí | K38: No | L38: No | M38: No | N38: No | O38: No
A39: BYJ004 | B39: BYJ004 | C39: Bebidas Frías | D39: Batidos & Jugos | E39: BYJ | F39: 9 | G39: 4 | H39: =(F39*100)+G39 -> 904 | I39: 3 | J39: Sí | K39: No | L39: No | M39: No | N39: No | O39: No
A40: BYJ005 | B40: BYJ005 | C40: Bebidas Frías | D40: Batidos & Jugos | E40: BYJ | F40: 9 | G40: 5 | H40: =(F40*100)+G40 -> 905 | I40: 3 | J40: Sí | K40: No | L40: No | M40: No | N40: No | O40: No
A41: BYJ006 | B41: BYJ006 | C41: Bebidas Frías | D41: Batidos & Jugos | E41: BYJ | F41: 9 | G41: 6 | H41: =(F41*100)+G41 -> 906 | I41: 3 | J41: Sí | K41: No | L41: Sí | M41: No | N41: No | O41: No
A42: ADI001 | B42: ADI001 | C42: Personalización | D42: Adicionales | E42: ADI | F42: 10 | G42: 1 | H42: =(F42*100)+G42 -> 1001 | I42: 3 | J42: Sí | K42: No | L42: No | M42: No | N42: No | O42: No
A43: ADI002 | B43: ADI002 | C43: Personalización | D43: Adicionales | E43: ADI | F43: 10 | G43: 2 | H43: =(F43*100)+G43 -> 1002 | I43: 3 | J43: Sí | K43: No | L43: No | M43: No | N43: No | O43: No
A44: STC001 | B44: STC001 | C44: Sin TACC | D44: Sin TACC | E44: STC | F44: 11 | G44: 1 | H44: =(F44*100)+G44 -> 1101 | I44: 3 | J44: Sí | K44: No | L44: No | M44: No | N44: No | O44: No | Q44: Validar certificación, proveedor y riesgo de contaminación cruzada.
A45: STC002 | B45: STC002 | C45: Sin TACC | D45: Sin TACC | E45: STC | F45: 11 | G45: 2 | H45: =(F45*100)+G45 -> 1102 | I45: 3 | J45: Sí | K45: No | L45: No | M45: No | N45: No | O45: No | Q45: Validar certificación, proveedor y riesgo de contaminación cruzada.
A46: STC003 | B46: STC003 | C46: Sin TACC | D46: Sin TACC | E46: STC | F46: 11 | G46: 3 | H46: =(F46*100)+G46 -> 1103 | I46: 3 | J46: Sí | K46: No | L46: No | M46: No | N46: No | O46: No | Q46: Validar certificación, proveedor y riesgo de contaminación cruzada.
A47: STC004 | B47: STC004 | C47: Sin TACC | D47: Sin TACC | E47: STC | F47: 11 | G47: 4 | H47: =(F47*100)+G47 -> 1104 | I47: 3 | J47: Sí | K47: No | L47: No | M47: No | N47: No | O47: No | Q47: Validar certificación, proveedor y riesgo de contaminación cruzada.
A48: TYT001 | B48: TYT001 | C48: Pastelería | D48: Tortas & Tartas | E48: TYT | F48: 12 | G48: 1 | H48: =(F48*100)+G48 -> 1201 | I48: 4 | J48: Sí | K48: Sí | L48: Sí | M48: No | N48: No | O48: No | P48: Producto insignia
A49: TYT002 | B49: TYT002 | C49: Pastelería | D49: Tortas & Tartas | E49: TYT | F49: 12 | G49: 2 | H49: =(F49*100)+G49 -> 1202 | I49: 4 | J49: Sí | K49: No | L49: Sí | M49: No | N49: No | O49: No
A50: TYT003 | B50: TYT003 | C50: Pastelería | D50: Tortas & Tartas | E50: TYT | F50: 12 | G50: 3 | H50: =(F50*100)+G50 -> 1203 | I50: 4 | J50: Sí | K50: No | L50: No | M50: No | N50: No | O50: No
A51: TYT004 | B51: TYT004 | C51: Pastelería | D51: Tortas & Tartas | E51: TYT | F51: 12 | G51: 4 | H51: =(F51*100)+G51 -> 1204 | I51: 4 | J51: Sí | K51: No | L51: No | M51: No | N51: No | O51: No
A52: TYT005 | B52: TYT005 | C52: Pastelería | D52: Tortas & Tartas | E52: TYT | F52: 12 | G52: 5 | H52: =(F52*100)+G52 -> 1205 | I52: 4 | J52: Sí | K52: No | L52: No | M52: No | N52: No | O52: No
A53: TYT006 | B53: TYT006 | C53: Pastelería | D53: Tortas & Tartas | E53: TYT | F53: 12 | G53: 6 | H53: =(F53*100)+G53 -> 1206 | I53: 4 | J53: Sí | K53: No | L53: No | M53: No | N53: No | O53: No
A54: TYT007 | B54: TYT007 | C54: Pastelería | D54: Tortas & Tartas | E54: TYT | F54: 12 | G54: 7 | H54: =(F54*100)+G54 -> 1207 | I54: 4 | J54: Sí | K54: Sí | L54: Sí | M54: No | N54: No | O54: No | P54: Creación de la casa
A55: SAT001 | B55: SAT001 | C55: Salados | D55: Sándwiches & Tostones | E55: SAT | F55: 13 | G55: 1 | H55: =(F55*100)+G55 -> 1301 | I55: 4 | J55: Sí | K55: No | L55: No | M55: No | N55: No | O55: No
A56: SAT002 | B56: SAT002 | C56: Salados | D56: Sándwiches & Tostones | E56: SAT | F56: 13 | G56: 2 | H56: =(F56*100)+G56 -> 1302 | I56: 4 | J56: Sí | K56: No | L56: No | M56: No | N56: No | O56: No
A57: SAT003 | B57: SAT003 | C57: Salados | D57: Sándwiches & Tostones | E57: SAT | F57: 13 | G57: 3 | H57: =(F57*100)+G57 -> 1303 | I57: 4 | J57: Sí | K57: Sí | L57: Sí | M57: No | N57: No | O57: No | P57: Firma Amelí
A58: SAT004 | B58: SAT004 | C58: Salados | D58: Sándwiches & Tostones | E58: SAT | F58: 13 | G58: 4 | H58: =(F58*100)+G58 -> 1304 | I58: 4 | J58: Sí | K58: No | L58: Sí | M58: No | N58: No | O58: No
A59: SAT005 | B59: SAT005 | C59: Salados | D59: Sándwiches & Tostones | E59: SAT | F59: 13 | G59: 5 | H59: =(F59*100)+G59 -> 1305 | I59: 4 | J59: Sí | K59: Sí | L59: Sí | M59: No | N59: No | O59: No | P59: Especialidad salada

Sheet 03_Categorías
A1: Arquitectura de categorías · Jerarquía multilingüe
A2: La columna «Orden» controla la navegación del menú mobile-first. Los grupos permiten mostrar una portada breve sin perder profundidad.
A4: Código | B4: Orden | C4: Grupo ES | D4: Grupo EN | E4: Grupo PT | F4: Grupo FR | G4: Grupo IT | H4: Categoría ES | I4: Categoría EN | J4: Categoría PT | K4: Categoría FR | L4: Categoría IT | M4: Cantidad de productos | N4: Página fuente | O4: Visible
A5: DYM | B5: 1 | C5: Desayunos & Brunch | D5: Breakfast & Brunch | E5: Café da manhã & brunch | F5: Petit-déjeuner & brunch | G5: Colazione & brunch | H5: Desayunos & Meriendas | I5: Breakfast & Afternoon Tea | J5: Café da manhã & lanche da tarde | K5: Petit-déjeuner & goûter | L5: Colazione & merenda | M5: =COUNTIF(02_Productos_MASTER!$E$5:$E$59,A5) -> 4 | N5: 2 | O5: Sí
A6: DEL | B6: 2 | C6: Desayunos & Brunch | D6: Breakfast & Brunch | E6: Café da manhã & brunch | F6: Petit-déjeuner & brunch | G6: Colazione & brunch | H6: Delicias | I6: Bakery & Light Bites | J6: Delícias & lanches leves | K6: Douceurs & petites bouchées | L6: Delizie & spuntini | M6: =COUNTIF(02_Productos_MASTER!$E$5:$E$59,A6) -> 7 | N6: 2 | O6: Sí
A7: TEH | B7: 3 | C7: Té & Infusiones | D7: Tea & Infusions | E7: Chás & infusões | F7: Thés & infusions | G7: Tè & infusi | H7: Té en Hebras | I7: Loose-Leaf Tea | J7: Chás de folhas soltas | K7: Thés en feuilles | L7: Tè in foglia | M7: =COUNTIF(02_Productos_MASTER!$E$5:$E$59,A7) -> 1 | N7: 2 | O7: Sí
A8: TIS | B8: 4 | C8: Té & Infusiones | D8: Tea & Infusions | E8: Chás & infusões | F8: Thés & infusions | G8: Tè & infusi | H8: Tisanas | I8: Herbal Infusions | J8: Infusões de ervas | K8: Tisanes | L8: Tisane | M8: =COUNTIF(02_Productos_MASTER!$E$5:$E$59,A8) -> 3 | N8: 2 | O8: Sí
A9: BLE | B9: 5 | C9: Té & Infusiones | D9: Tea & Infusions | E9: Chás & infusões | F9: Thés & infusions | G9: Tè & infusi | H9: Blends | I9: Signature Tea Blends | J9: Blends autorais | K9: Mélanges signature | L9: Miscele d’autore | M9: =COUNTIF(02_Productos_MASTER!$E$5:$E$59,A9) -> 4 | N9: 2 | O9: Sí
A10: ESP | B10: 6 | C10: Té & Infusiones | D10: Tea & Infusions | E10: Chás & infusões | F10: Thés & infusions | G10: Tè & infusi | H10: Especiales | I10: Hot Specialities | J10: Especialidades quentes | K10: Spécialités chaudes | L10: Specialità calde | M10: =COUNTIF(02_Productos_MASTER!$E$5:$E$59,A10) -> 2 | N10: 2 | O10: Sí
A11: CCL | B11: 7 | C11: Cafetería | D11: Coffee | E11: Cafeteria | F11: Café | G11: Caffetteria | H11: Café Clásico | I11: Classic Coffee | J11: Cafés clássicos | K11: Cafés classiques | L11: Caffè classici | M11: =COUNTIF(02_Productos_MASTER!$E$5:$E$59,A11) -> 7 | N11: 3 | O11: Sí
A12: CFR | B12: 8 | C12: Cafetería | D12: Coffee | E12: Cafeteria | F12: Café | G12: Caffetteria | H12: Café Frío | I12: Iced Coffee | J12: Cafés gelados | K12: Cafés glacés | L12: Caffè freddi | M12: =COUNTIF(02_Productos_MASTER!$E$5:$E$59,A12) -> 3 | N12: 3 | O12: Sí
A13: BYJ | B13: 9 | C13: Bebidas Frías | D13: Cold Drinks | E13: Bebidas frias | F13: Boissons fraîches | G13: Bevande fredde | H13: Batidos & Jugos | I13: Smoothies & Juices | J13: Vitaminas & sucos | K13: Smoothies & jus | L13: Frullati & succhi | M13: =COUNTIF(02_Productos_MASTER!$E$5:$E$59,A13) -> 6 | N13: 3 | O13: Sí
A14: ADI | B14: 10 | C14: Personalización | D14: Customisation | E14: Personalização | F14: Personnalisation | G14: Personalizzazione | H14: Adicionales | I14: Milk Options | J14: Opções de leite | K14: Options de lait | L14: Opzioni latte | M14: =COUNTIF(02_Productos_MASTER!$E$5:$E$59,A14) -> 2 | N14: 3 | O14: Sí
A15: STC | B15: 11 | C15: Sin TACC | D15: Gluten-Free | E15: Sem glúten | F15: Sans gluten | G15: Senza glutine | H15: Sin TACC | I15: Gluten-Free Selection | J15: Seleção sem glúten | K15: Sélection sans gluten | L15: Selezione senza glutine | M15: =COUNTIF(02_Productos_MASTER!$E$5:$E$59,A15) -> 4 | N15: 3 | O15: Sí
A16: TYT | B16: 12 | C16: Pastelería | D16: Cakes & Pastries | E16: Bolos & tortas | F16: Gâteaux & tartes | G16: Torte & dolci | H16: Tortas & Tartas | I16: Cakes & Tarts | J16: Bolos & tortas | K16: Gâteaux & tartes | L16: Torte & crostate | M16: =COUNTIF(02_Productos_MASTER!$E$5:$E$59,A16) -> 7 | N16: 4 | O16: Sí
A17: SAT | B17: 13 | C17: Salados | D17: Savoury | E17: Salgados | F17: Salé | G17: Salati | H17: Sándwiches & Tostones | I17: Sandwiches & Open Toasts | J17: Sanduíches & tostadas | K17: Sandwichs & tartines | L17: Panini & bruschette | M17: =COUNTIF(02_Productos_MASTER!$E$5:$E$59,A17) -> 5 | N17: 4 | O17: Sí

Sheet 04_Precios
A1: Precios y rentabilidad básica
A2: Completar únicamente las celdas crema. El precio en USD, el margen bruto y el estado de carga se calculan automáticamente.
A4: ID | B4: Producto ES-AR | C4: Moneda | D4: Precio local | E4: Precio delivery | F4: Precio promocional | G4: Precio de referencia USD | H4: Costo unitario | I4: Margen bruto | J4: Margen bruto % | K4: IVA incluido | L4: Fecha actualización | M4: Estado de carga | N4: Observaciones
A5: DYM001 | B5: Avocado | C5: ARS | G5: =IF(OR(D5="",TC_USD=""),"",D5/TC_USD) | I5: =IF(OR(D5="",H5=""),"",D5-H5) | J5: =IFERROR(I5/D5,"") | K5: Sí | L5: =IF(D5="","",TODAY()) | M5: =IF(D5="","Pendiente",IF(H5="","Precio cargado; falta costo","Completo")) -> Pendiente
A6: DYM002 | B6: Desayuno clásico | C6: ARS | G6: =IF(OR(D6="",TC_USD=""),"",D6/TC_USD) | I6: =IF(OR(D6="",H6=""),"",D6-H6) | J6: =IFERROR(I6/D6,"") | K6: Sí | L6: =IF(D6="","",TODAY()) | M6: =IF(D6="","Pendiente",IF(H6="","Precio cargado; falta costo","Completo")) -> Pendiente
A7: DYM003 | B7: Desayuno mendocino | C7: ARS | G7: =IF(OR(D7="",TC_USD=""),"",D7/TC_USD) | I7: =IF(OR(D7="",H7=""),"",D7-H7) | J7: =IFERROR(I7/D7,"") | K7: Sí | L7: =IF(D7="","",TODAY()) | M7: =IF(D7="","Pendiente",IF(H7="","Precio cargado; falta costo","Completo")) -> Pendiente
A8: DYM004 | B8: Desayuno saludable | C8: ARS | G8: =IF(OR(D8="",TC_USD=""),"",D8/TC_USD) | I8: =IF(OR(D8="",H8=""),"",D8-H8) | J8: =IFERROR(I8/D8,"") | K8: Sí | L8: =IF(D8="","",TODAY()) | M8: =IF(D8="","Pendiente",IF(H8="","Precio cargado; falta costo","Completo")) -> Pendiente
A9: DEL001 | B9: Bowl de huevos | C9: ARS | G9: =IF(OR(D9="",TC_USD=""),"",D9/TC_USD) | I9: =IF(OR(D9="",H9=""),"",D9-H9) | J9: =IFERROR(I9/D9,"") | K9: Sí | L9: =IF(D9="","",TODAY()) | M9: =IF(D9="","Pendiente",IF(H9="","Precio cargado; falta costo","Completo")) -> Pendiente
A10: DEL002 | B10: Bowl de frutas | C10: ARS | G10: =IF(OR(D10="",TC_USD=""),"",D10/TC_USD) | I10: =IF(OR(D10="",H10=""),"",D10-H10) | J10: =IFERROR(I10/D10,"") | K10: Sí | L10: =IF(D10="","",TODAY()) | M10: =IF(D10="","Pendiente",IF(H10="","Precio cargado; falta costo","Completo")) -> Pendiente
A11: DEL003 | B11: Chipá | C11: ARS | G11: =IF(OR(D11="",TC_USD=""),"",D11/TC_USD) | I11: =IF(OR(D11="",H11=""),"",D11-H11) | J11: =IFERROR(I11/D11,"") | K11: Sí | L11: =IF(D11="","",TODAY()) | M11: =IF(D11="","Pendiente",IF(H11="","Precio cargado; falta costo","Completo")) -> Pendiente
A12: DEL004 | B12: Medialunas | C12: ARS | G12: =IF(OR(D12="",TC_USD=""),"",D12/TC_USD) | I12: =IF(OR(D12="",H12=""),"",D12-H12) | J12: =IFERROR(I12/D12,"") | K12: Sí | L12: =IF(D12="","",TODAY()) | M12: =IF(D12="","Pendiente",IF(H12="","Precio cargado; falta costo","Completo")) -> Pendiente
A13: DEL005 | B13: Mini budines | C13: ARS | G13: =IF(OR(D13="",TC_USD=""),"",D13/TC_USD) | I13: =IF(OR(D13="",H13=""),"",D13-H13) | J13: =IFERROR(I13/D13,"") | K13: Sí | L13: =IF(D13="","",TODAY()) | M13: =IF(D13="","Pendiente",IF(H13="","Precio cargado; falta costo","Completo")) -> Pendiente
A14: DEL006 | B14: Raspaditas mendocinas | C14: ARS | G14: =IF(OR(D14="",TC_USD=""),"",D14/TC_USD) | I14: =IF(OR(D14="",H14=""),"",D14-H14) | J14: =IFERROR(I14/D14,"") | K14: Sí | L14: =IF(D14="","",TODAY()) | M14: =IF(D14="","Pendiente",IF(H14="","Precio cargado; falta costo","Completo")) -> Pendiente
A15: DEL007 | B15: Smoothie bowl | C15: ARS | G15: =IF(OR(D15="",TC_USD=""),"",D15/TC_USD) | I15: =IF(OR(D15="",H15=""),"",D15-H15) | J15: =IFERROR(I15/D15,"") | K15: Sí | L15: =IF(D15="","",TODAY()) | M15: =IF(D15="","Pendiente",IF(H15="","Precio cargado; falta costo","Completo")) -> Pendiente
A16: TEH001 | B16: Selección de té en hebras | C16: ARS | G16: =IF(OR(D16="",TC_USD=""),"",D16/TC_USD) | I16: =IF(OR(D16="",H16=""),"",D16-H16) | J16: =IFERROR(I16/D16,"") | K16: Sí | L16: =IF(D16="","",TODAY()) | M16: =IF(D16="","Pendiente",IF(H16="","Precio cargado; falta costo","Completo")) -> Pendiente
... A59: SAT005 | B59: Pistachero | C59: ARS | G59: =IF(OR(D59="",TC_USD=""),"",D59/TC_USD) | I59: =IF(OR(D59="",H59=""),"",D59-H59) | J59: =IFERROR(I59/D59,"") | K59: Sí | L59: =IF(D59="","",TODAY()) | M59: =IF(D59="","Pendiente",IF(H59="","Precio cargado; falta costo","Completo")) -> Pendiente

Sheet 05_Gastronomía
A1: Información gastronómica y operativa
A2: Los campos «Verificar» deben validarse con cocina y proveedores antes de publicar o automatizar el menú.
A4: ID | B4: Producto ES-AR | C4: Tipo | D4: Temperatura | E4: Formato de servicio | F4: Porciones | G4: Tiempo de preparación (min) | H4: Origen | I4: Elaboración propia | J4: Producto tercerizado | K4: Disponible para llevar | L4: Notas operativas
A5: DYM001 | B5: Avocado | C5: Combo de desayuno | D5: Mixta | E5: Porción individual | F5: 1 | I5: Verificar | J5: Verificar | K5: Verificar
A6: DYM002 | B6: Desayuno clásico | C6: Combo de desayuno | D6: Mixta | E6: Porción individual | F6: 1 | I6: Verificar | J6: Verificar | K6: Verificar
A7: DYM003 | B7: Desayuno mendocino | C7: Combo de desayuno regional | D7: Mixta | E7: Porción individual | F7: 1 | H7: Mendoza, Argentina | I7: Verificar | J7: Verificar | K7: Verificar
A8: DYM004 | B8: Desayuno saludable | C8: Combo de desayuno | D8: Mixta | E8: Porción individual | F8: 1 | I8: Verificar | J8: Verificar | K8: Verificar
A9: DEL001 | B9: Bowl de huevos | C9: Plato ligero | D9: Caliente | E9: Porción individual | F9: 1 | I9: Verificar | J9: Verificar | K9: Sí | L9: Confirmar receta y acompañamientos.
A10: DEL002 | B10: Bowl de frutas | C10: Plato ligero | D10: Fría | E10: Porción individual | F10: 1 | I10: Verificar | J10: Verificar | K10: Sí
A11: DEL003 | B11: Chipá | C11: Panificado salado | D11: Caliente/Ambiente | E11: Unidad o porción | F11: Verificar | H11: Región guaraní / Argentina | I11: Verificar | J11: Verificar | K11: Sí
A12: DEL004 | B12: Medialunas | C12: Panificado dulce | D12: Caliente/Ambiente | E12: Unidad o porción | F12: Verificar | H12: Argentina | I12: Verificar | J12: Verificar | K12: Sí
A13: DEL005 | B13: Mini budines | C13: Pastelería individual | D13: Ambiente | E13: Unidad | F13: 1 | I13: Verificar | J13: Verificar | K13: Sí | L13: Los ingredientes varían según el sabor.
A14: DEL006 | B14: Raspaditas mendocinas | C14: Panificado regional | D14: Ambiente | E14: Unidad o porción | F14: Verificar | H14: Mendoza, Argentina | I14: Verificar | J14: Verificar | K14: Sí
A15: DEL007 | B15: Smoothie bowl | C15: Plato ligero | D15: Fría | E15: Porción individual | F15: 1 | I15: Verificar | J15: Verificar | K15: Sí | L15: Confirmar ingredientes, toppings y base líquida.
A16: TEH001 | B16: Selección de té en hebras | C16: Infusión | D16: Caliente | E16: Tetera o taza | F16: 1 | I16: Verificar | J16: Verificar | K16: Sí
A17: TIS001 | B17: Tisana 1 · Cedrón & lavanda | C17: Tisana | D17: Caliente | E17: Tetera o taza | F17: 1 | I17: Verificar | J17: Verificar | K17: Sí
A18: TIS002 | B18: Tisana 2 · Limón & menta | C18: Tisana | D18: Caliente | E18: Tetera o taza | F18: 1 | I18: Verificar | J18: Verificar | K18: Sí
A19: TIS003 | B19: Tisana 3 · Manzanilla & melisa | C19: Tisana | D19: Caliente | E19: Tetera o taza | F19: 1 | I19: Verificar | J19: Verificar | K19: Sí
A20: BLE001 | B20: Del bosque | C20: Blend de té | D20: Caliente | E20: Tetera o taza | F20: 1 | I20: Verificar | J20: Verificar | K20: Sí
A21: BLE002 | B21: Detox | C21: Blend de té | D21: Caliente | E21: Tetera o taza | F21: 1 | I21: Verificar | J21: Verificar | K21: Sí
A22: BLE003 | B22: Dorado | C22: Blend de té | D22: Caliente | E22: Tetera o taza | F22: 1 | I22: Verificar | J22: Verificar | K22: Sí
A23: BLE004 | B23: Love | C23: Blend de té | D23: Caliente | E23: Tetera o taza | F23: 1 | I23: Verificar | J23: Verificar | K23: Sí
A24: ESP001 | B24: Submarino | C24: Bebida caliente | D24: Caliente | E24: Taza o vaso | F24: 1 | H24: Argentina | I24: Verificar | J24: Verificar | K24: Sí
A25: ESP002 | B25: Leche dorada | C25: Bebida caliente | D25: Caliente | E25: Taza o vaso | F25: 1 | I25: Verificar | J25: Verificar | K25: Sí
A26: CCL001 | B26: Americano | C26: Café | D26: Caliente | E26: Taza | F26: 1 | I26: Verificar | J26: Verificar | K26: Sí
A27: CCL002 | B27: Cortado | C27: Café con leche | D27: Caliente | E27: Taza | F27: 1 | I27: Verificar | J27: Verificar | K27: Sí
A28: CCL003 | B28: Café con leche | C28: Café con leche | D28: Caliente | E28: Taza | F28: 1 | I28: Verificar | J28: Verificar | K28: Sí
A29: CCL004 | B29: Lágrima | C29: Bebida con café | D29: Caliente | E29: Taza | F29: 1 | H29: Argentina | I29: Verificar | J29: Verificar | K29: Sí
A30: CCL005 | B30: Macchiato | C30: Café con leche | D30: Caliente | E30: Taza | F30: 1 | I30: Verificar | J30: Verificar | K30: Sí
A31: CCL006 | B31: Cappuccino | C31: Café con leche | D31: Caliente | E31: Taza | F31: 1 | I31: Verificar | J31: Verificar | K31: Sí
A32: CCL007 | B32: Moca | C32: Café con chocolate | D32: Caliente | E32: Taza | F32: 1 | I32: Verificar | J32: Verificar | K32: Sí
A33: CFR001 | B33: Cold brew | C33: Café frío | D33: Fría | E33: Vaso | F33: 1 | I33: Verificar | J33: Verificar | K33: Sí
A34: CFR002 | B34: Iced latte | C34: Café frío con leche | D34: Fría | E34: Vaso | F34: 1 | I34: Verificar | J34: Verificar | K34: Sí
A35: CFR003 | B35: Frappé de dulce de leche | C35: Café frío | D35: Fría | E35: Vaso | F35: 1 | I35: Verificar | J35: Verificar | K35: Sí
A36: BYJ001 | B36: Batido de banana | C36: Batido | D36: Fría | E36: Vaso | F36: 1 | I36: Verificar | J36: Verificar | K36: Sí | L36: Confirmar si la base contiene leche.
A37: BYJ002 | B37: Batido de frutos rojos | C37: Batido | D37: Fría | E37: Vaso o jarra | F37: Verificar | I37: Verificar | J37: Verificar | K37: Sí
A38: BYJ003 | B38: Limonada detox | C38: Limonada | D38: Fría | E38: Vaso o jarra | F38: Verificar | I38: Verificar | J38: Verificar | K38: Sí
A39: BYJ004 | B39: Limonada Jamaica | C39: Limonada | D39: Fría | E39: Vaso o jarra | F39: Verificar | I39: Verificar | J39: Verificar | K39: Sí
A40: BYJ005 | B40: Jugo de naranja | C40: Jugo | D40: Fría | E40: Vaso | F40: 1 | I40: Verificar | J40: Verificar | K40: Sí
A41: BYJ006 | B41: Tropical | C41: Batido | D41: Fría | E41: Vaso o jarra | F41: Verificar | I41: Verificar | J41: Verificar | K41: Sí
A42: ADI001 | B42: Leche vegetal | C42: Adicional | D42: Según bebida | E42: Adicional | F42: 1 | I42: Verificar | J42: Verificar | K42: Sí
A43: ADI002 | B43: Leche sin lactosa | C43: Adicional | D43: Según bebida | E43: Adicional | F43: 1 | I43: Verificar | J43: Verificar | K43: Sí
A44: STC001 | B44: Postres sin TACC | C44: Postre | D44: Fría | E44: Porción individual | F44: 1 | I44: No | J44: Sí | K44: Sí | L44: Validar certificación, proveedor y riesgo de contaminación cruzada.
A45: STC002 | B45: Pasta frola sin TACC | C45: Tarta | D45: Fría/Ambiente | E45: Porción individual | F45: 1 | I45: No | J45: Sí | K45: Sí | L45: Validar certificación, proveedor y riesgo de contaminación cruzada.
A46: STC003 | B46: Tarta de coco y dulce de leche sin TACC | C46: Tarta | D46: Fría/Ambiente | E46: Porción individual | F46: 1 | I46: No | J46: Sí | K46: Sí | L46: Validar certificación, proveedor y riesgo de contaminación cruzada.
A47: STC004 | B47: Alfacookie sin TACC | C47: Pastelería individual | D47: Ambiente | E47: Unidad | F47: 1 | I47: No | J47: Sí | K47: Sí | L47: Validar certificación, proveedor y riesgo de contaminación cruzada.
A48: TYT001 | B48: Torta Amelí | C48: Torta | D48: Fría/Ambiente | E48: Porción | F48: 1 | I48: Verificar | J48: Verificar | K48: Sí
A49: TYT002 | B49: Marquise | C49: Torta | D49: Fría | E49: Porción | F49: 1 | I49: Verificar | J49: Verificar | K49: Sí
A50: TYT003 | B50: Cheesecake de frutos rojos | C50: Torta | D50: Fría | E50: Porción | F50: 1 | I50: Verificar | J50: Verificar | K50: Sí
A51: TYT004 | B51: Red velvet | C51: Torta | D51: Fría | E51: Porción | F51: 1 | I51: Verificar | J51: Verificar | K51: Sí
A52: TYT005 | B52: Key lime pie | C52: Tarta | D52: Fría | E52: Porción | F52: 1 | I52: Verificar | J52: Verificar | K52: Sí
A53: TYT006 | B53: Sablée de almendras | C53: Mini torta | D53: Fría | E53: Porción individual | F53: 1 | I53: Verificar | J53: Verificar | K53: Sí
A54: TYT007 | B54: Franuí del bosque | C54: Torta/Brownie | D54: Fría/Ambiente | E54: Porción | F54: 1 | I54: Verificar | J54: Verificar | K54: Sí
A55: SAT001 | B55: Bagel | C55: Sándwich | D55: Caliente | E55: Porción individual | F55: 1 | I55: Verificar | J55: Verificar | K55: Sí
A56: SAT002 | B56: Tostado de jamón y queso | C56: Sándwich tostado | D56: Caliente | E56: Porción individual | F56: 1 | I56: Verificar | J56: Verificar | K56: Sí
A57: SAT003 | B57: Tostón Amelí | C57: Tostón | D57: Caliente | E57: Porción individual | F57: 1 | I57: Verificar | J57: Verificar | K57: Sí
A58: SAT004 | B58: Tostón de palta y huevo | C58: Tostón | D58: Caliente | E58: Porción individual | F58: 1 | I58: Verificar | J58: Verificar | K58: Sí
A59: SAT005 | B59: Pistachero | C59: Sándwich | D59: Caliente | E59: Porción individual | F59: 1 | I59: Verificar | J59: Verificar | K59: Sí

Sheet 06_Ingredientes
A1: Ingredientes declarados · Matriz preliminar
A2: La información surge del menú original y de descripciones editoriales. Debe cruzarse con recetas, fichas técnicas y etiquetas antes de utilizarse para alérgenos.
A4: ID | B4: Producto ES-AR | C4: Ingrediente 1 | D4: Ingrediente 2 | E4: Ingrediente 3 | F4: Ingrediente 4 | G4: Ingrediente 5 | H4: Ingrediente 6 | I4: Ingrediente 7 | J4: Ingrediente 8 | K4: Ingrediente 9 | L4: Ingrediente 10 | M4: Ingrediente 11 | N4: Ingrediente 12 | O4: Estado de revisión | P4: Observaciones
A5: DYM001 | B5: Avocado | C5: Huevos | D5: Palta | E5: Pan tostado | F5: Queso crema | G5: Café o té | H5: Jugo de naranja | O5: Pendiente de validación
A6: DYM002 | B6: Desayuno clásico | C6: Pan tostado | D6: Queso crema | E6: Mermelada | F6: Café o té | G6: Jugo de naranja | O6: Pendiente de validación
A7: DYM003 | B7: Desayuno mendocino | C7: Raspaditas mendocinas | D7: Café o té | E7: Jugo de naranja | O7: Pendiente de validación
A8: DYM004 | B8: Desayuno saludable | C8: Yogur | D8: Frutas de estación | E8: Granola | F8: Frutos secos | G8: Miel | H8: Coco | I8: Café o té | J8: Jugo de naranja | O8: Pendiente de validación
A9: DEL001 | B9: Bowl de huevos | C9: Huevos | D9: Acompañamientos a confirmar | O9: Pendiente de validación | P9: Confirmar receta y acompañamientos.
A10: DEL002 | B10: Bowl de frutas | C10: Frutas de estación | O10: Pendiente de validación
A11: DEL003 | B11: Chipá | C11: Almidón de mandioca | D11: Queso | E11: Huevos | F11: Leche o materia grasa a verificar | O11: Pendiente de validación
A12: DEL004 | B12: Medialunas | C12: Harina de trigo | D12: Materia grasa | E12: Azúcar | F12: Levadura | G12: Huevos o leche a verificar | O12: Pendiente de validación
A13: DEL005 | B13: Mini budines | C13: Harina | D13: Huevos | E13: Azúcar | F13: Materia grasa | G13: Sabores a confirmar | O13: Pendiente de validación | P13: Los ingredientes varían según el sabor.
A14: DEL006 | B14: Raspaditas mendocinas | C14: Harina de trigo | D14: Materia grasa | E14: Agua | F14: Sal | O14: Pendiente de validación
A15: DEL007 | B15: Smoothie bowl | C15: Frutas | D15: Toppings a confirmar | O15: Pendiente de validación | P15: Confirmar ingredientes, toppings y base líquida.
A16: TEH001 | B16: Selección de té en hebras | C16: Té negro, pu-erh o verde | D16: Agua | O16: Pendiente de validación
A17: TIS001 | B17: Tisana 1 · Cedrón & lavanda | C17: Cedrón | D17: Lavanda | E17: Manzanilla | F17: Melisa | G17: Agua | O17: Pendiente de validación
A18: TIS002 | B18: Tisana 2 · Limón & menta | C18: Limón | D18: Menta | E18: Salvia blanca | F18: Agua | O18: Pendiente de validación
A19: TIS003 | B19: Tisana 3 · Manzanilla & melisa | C19: Manzanilla | D19: Melisa | E19: Menta | F19: Agua | O19: Pendiente de validación
A20: BLE001 | B20: Del bosque | C20: Té negro | D20: Cacao | E20: Naranja | F20: Agua | O20: Pendiente de validación
A21: BLE002 | B21: Detox | C21: Té verde | D21: Jengibre | E21: Limón | F21: Menta | G21: Agua | O21: Pendiente de validación
A22: BLE003 | B22: Dorado | C22: Té verde | D22: Caléndula | E22: Durazno | F22: Limón | G22: Agua | O22: Pendiente de validación
A23: BLE004 | B23: Love | C23: Té pu-erh | D23: Hibisco | E23: Pomelo | F23: Agua | O23: Pendiente de validación
A24: ESP001 | B24: Submarino | C24: Leche | D24: Chocolate | O24: Pendiente de validación
A25: ESP002 | B25: Leche dorada | C25: Leche | D25: Anís estrellado | E25: Canela | F25: Clavo de olor | G25: Cúrcuma | H25: Jengibre | I25: Pimienta negra | O25: Pendiente de validación
A26: CCL001 | B26: Americano | C26: Café espresso | D26: Agua | O26: Pendiente de validación
A27: CCL002 | B27: Cortado | C27: Café espresso | D27: Leche | O27: Pendiente de validación
A28: CCL003 | B28: Café con leche | C28: Café | D28: Leche | O28: Pendiente de validación
A29: CCL004 | B29: Lágrima | C29: Leche | D29: Café | O29: Pendiente de validación
A30: CCL005 | B30: Macchiato | C30: Café espresso | D30: Espuma de leche | O30: Pendiente de validación
A31: CCL006 | B31: Cappuccino | C31: Café | D31: Leche | E31: Espuma de leche | O31: Pendiente de validación
A32: CCL007 | B32: Moca | C32: Café | D32: Chocolate | E32: Leche | F32: Espuma de leche | O32: Pendiente de validación
A33: CFR001 | B33: Cold brew | C33: Café | D33: Agua | O33: Pendiente de validación
A34: CFR002 | B34: Iced latte | C34: Café espresso | D34: Leche | E34: Hielo | O34: Pendiente de validación
A35: CFR003 | B35: Frappé de dulce de leche | C35: Café | D35: Leche | E35: Hielo | F35: Dulce de leche | O35: Pendiente de validación
A36: BYJ001 | B36: Batido de banana | C36: Banana | D36: Base líquida a confirmar | O36: Pendiente de validación | P36: Confirmar si la base contiene leche.
A37: BYJ002 | B37: Batido de frutos rojos | C37: Frutos rojos | D37: Jugo de naranja | O37: Pendiente de validación
A38: BYJ003 | B38: Limonada detox | C38: Agua | D38: Chía | E38: Jengibre | F38: Limón | G38: Menta | O38: Pendiente de validación
A39: BYJ004 | B39: Limonada Jamaica | C39: Agua | D39: Arándanos | E39: Hibisco | F39: Limón | O39: Pendiente de validación
A40: BYJ005 | B40: Jugo de naranja | C40: Naranja | O40: Pendiente de validación
A41: BYJ006 | B41: Tropical | C41: Mango | D41: Maracuyá | E41: Ananá | F41: Naranja | O41: Pendiente de validación
A42: ADI001 | B42: Leche vegetal | C42: Bebida vegetal a confirmar | O42: Pendiente de validación
A43: ADI002 | B43: Leche sin lactosa | C43: Leche sin lactosa | O43: Pendiente de validación
A44: STC001 | B44: Postres sin TACC | C44: Ingredientes según postre | D44: Producto tercerizado | O44: Pendiente de validación | P44: Validar certificación, proveedor y riesgo de contaminación cruzada.
A45: STC002 | B45: Pasta frola sin TACC | C45: Premezcla sin gluten | D45: Membrillo | E45: Huevos y materia grasa a verificar | F45: Producto tercerizado | O45: Pendiente de validación | P45: Validar certificación, proveedor y riesgo de contaminación cruzada.
A46: STC003 | B46: Tarta de coco y dulce de leche sin TACC | C46: Premezcla sin gluten | D46: Dulce de leche | E46: Coco | F46: Producto tercerizado | O46: Pendiente de validación | P46: Validar certificación, proveedor y riesgo de contaminación cruzada.
A47: STC004 | B47: Alfacookie sin TACC | C47: Cookies sin gluten | D47: Dulce de leche | E47: Producto tercerizado | O47: Pendiente de validación | P47: Validar certificación, proveedor y riesgo de contaminación cruzada.
A48: TYT001 | B48: Torta Amelí | C48: Bizcochuelo de vainilla | D48: Chocolate blanco | E48: Limón | F48: Nueces | G48: Leche condensada | O48: Pendiente de validación
A49: TYT002 | B49: Marquise | C49: Bizcochuelo de chocolate | D49: Dulce de leche | E49: Crema chantilly | F49: Frutos rojos | O49: Pendiente de validación
A50: TYT003 | B50: Cheesecake de frutos rojos | C50: Galletas | D50: Queso crema | E50: Azúcar | F50: Frutos rojos | O50: Pendiente de validación
A51: TYT004 | B51: Red velvet | C51: Bizcochuelo de cacao | D51: Crema de queso | E51: Frutillas | O51: Pendiente de validación
A52: TYT005 | B52: Key lime pie | C52: Base crocante | D52: Lima | E52: Crema | F52: Leche condensada o huevos a verificar | O52: Pendiente de validación
A53: TYT006 | B53: Sablée de almendras | C53: Almendras | D53: Dulce de leche | E53: Crema | F53: Frutillas | G53: Harina o base a verificar | O53: Pendiente de validación
A54: TYT007 | B54: Franuí del bosque | C54: Brownie | D54: Dulce de leche | E54: Chocolate blanco | F54: Chocolate negro | G54: Dulce de frambuesa | H54: Frambuesas bañadas en chocolate | O54: Pendiente de validación
A55: SAT001 | B55: Bagel | C55: Bagel | D55: Tomate | E55: Panceta | F55: Palta | G55: Queso | H55: Huevo | O55: Pendiente de validación
A56: SAT002 | B56: Tostado de jamón y queso | C56: Pan de campo | D56: Jamón cocido | E56: Queso | O56: Pendiente de validación
A57: SAT003 | B57: Tostón Amelí | C57: Pan de campo | D57: Queso azul | E57: Peras | F57: Nueces | G57: Miel | O57: Pendiente de validación
A58: SAT004 | B58: Tostón de palta y huevo | C58: Pan de campo | D58: Queso crema | E58: Queso danbo | F58: Palta | G58: Huevo | H58: Semillas | O58: Pendiente de validación
A59: SAT005 | B59: Pistachero | C59: Pan a confirmar | D59: Mortadela | E59: Queso | F59: Manteca especiada | G59: Pistacho | O59: Pendiente de validación

Sheet 07_Alérgenos_Dietas
A1: Alérgenos y preferencias alimentarias
A2: Matriz deliberadamente conservadora: «Verificar» evita publicar afirmaciones inseguras. La validación final debe realizarla Amelí con recetas y etiquetas vigentes.
A4: ID | B4: Producto ES-AR | C4: Vegetariano | D4: Vegano | E4: Sin TACC | F4: Sin lactosa | G4: Contiene gluten | H4: Contiene leche | I4: Contiene huevo | J4: Contiene soja | K4: Contiene maní | L4: Contiene frutos secos | M4: Contiene sésamo | N4: Contiene pescado | O4: Contiene mariscos | P4: Contiene alcohol | Q4: Contiene cafeína | R4: Estado de validación | S4: Advertencia / observaciones
A5: DYM001 | B5: Avocado | C5: Verificar | D5: Verificar | E5: Verificar | F5: Verificar | G5: Verificar | H5: Verificar | I5: Verificar | J5: Verificar | K5: Verificar | L5: Verificar | M5: Verificar | N5: Verificar | O5: Verificar | P5: Verificar | Q5: Verificar | R5: Pendiente
A6: DYM002 | B6: Desayuno clásico | C6: Verificar | D6: Verificar | E6: Verificar | F6: Verificar | G6: Verificar | H6: Verificar | I6: Verificar | J6: Verificar | K6: Verificar | L6: Verificar | M6: Verificar | N6: Verificar | O6: Verificar | P6: Verificar | Q6: Verificar | R6: Pendiente
A7: DYM003 | B7: Desayuno mendocino | C7: Verificar | D7: Verificar | E7: Verificar | F7: Verificar | G7: Verificar | H7: Verificar | I7: Verificar | J7: Verificar | K7: Verificar | L7: Verificar | M7: Verificar | N7: Verificar | O7: Verificar | P7: Verificar | Q7: Verificar | R7: Pendiente
A8: DYM004 | B8: Desayuno saludable | C8: Verificar | D8: Verificar | E8: Verificar | F8: Verificar | G8: Verificar | H8: Verificar | I8: Verificar | J8: Verificar | K8: Verificar | L8: Verificar | M8: Verificar | N8: Verificar | O8: Verificar | P8: Verificar | Q8: Verificar | R8: Pendiente
A9: DEL001 | B9: Bowl de huevos | C9: Verificar | D9: Verificar | E9: Verificar | F9: Verificar | G9: Verificar | H9: Verificar | I9: Verificar | J9: Verificar | K9: Verificar | L9: Verificar | M9: Verificar | N9: Verificar | O9: Verificar | P9: Verificar | Q9: Verificar | R9: Pendiente | S9: Confirmar receta y acompañamientos.
A10: DEL002 | B10: Bowl de frutas | C10: Verificar | D10: Verificar | E10: Verificar | F10: Verificar | G10: Verificar | H10: Verificar | I10: Verificar | J10: Verificar | K10: Verificar | L10: Verificar | M10: Verificar | N10: Verificar | O10: Verificar | P10: Verificar | Q10: Verificar | R10: Pendiente
A11: DEL003 | B11: Chipá | C11: Verificar | D11: Verificar | E11: Verificar | F11: Verificar | G11: Verificar | H11: Verificar | I11: Verificar | J11: Verificar | K11: Verificar | L11: Verificar | M11: Verificar | N11: Verificar | O11: Verificar | P11: Verificar | Q11: Verificar | R11: Pendiente
A12: DEL004 | B12: Medialunas | C12: Verificar | D12: Verificar | E12: Verificar | F12: Verificar | G12: Verificar | H12: Verificar | I12: Verificar | J12: Verificar | K12: Verificar | L12: Verificar | M12: Verificar | N12: Verificar | O12: Verificar | P12: Verificar | Q12: Verificar | R12: Pendiente
A13: DEL005 | B13: Mini budines | C13: Verificar | D13: Verificar | E13: Verificar | F13: Verificar | G13: Verificar | H13: Verificar | I13: Verificar | J13: Verificar | K13: Verificar | L13: Verificar | M13: Verificar | N13: Verificar | O13: Verificar | P13: Verificar | Q13: Verificar | R13: Pendiente | S13: Los ingredientes varían según el sabor.
A14: DEL006 | B14: Raspaditas mendocinas | C14: Verificar | D14: Verificar | E14: Verificar | F14: Verificar | G14: Verificar | H14: Verificar | I14: Verificar | J14: Verificar | K14: Verificar | L14: Verificar | M14: Verificar | N14: Verificar | O14: Verificar | P14: Verificar | Q14: Verificar | R14: Pendiente
A15: DEL007 | B15: Smoothie bowl | C15: Verificar | D15: Verificar | E15: Verificar | F15: Verificar | G15: Verificar | H15: Verificar | I15: Verificar | J15: Verificar | K15: Verificar | L15: Verificar | M15: Verificar | N15: Verificar | O15: Verificar | P15: Verificar | Q15: Verificar | R15: Pendiente | S15: Confirmar ingredientes, toppings y base líquida.
A16: TEH001 | B16: Selección de té en hebras | C16: Verificar | D16: Verificar | E16: Verificar | F16: Verificar | G16: Verificar | H16: Verificar | I16: Verificar | J16: Verificar | K16: Verificar | L16: Verificar | M16: Verificar | N16: Verificar | O16: Verificar | P16: Verificar | Q16: Sí | R16: Pendiente
A17: TIS001 | B17: Tisana 1 · Cedrón & lavanda | C17: Verificar | D17: Verificar | E17: Verificar | F17: Verificar | G17: Verificar | H17: Verificar | I17: Verificar | J17: Verificar | K17: Verificar | L17: Verificar | M17: Verificar | N17: Verificar | O17: Verificar | P17: Verificar | Q17: No | R17: Pendiente
A18: TIS002 | B18: Tisana 2 · Limón & menta | C18: Verificar | D18: Verificar | E18: Verificar | F18: Verificar | G18: Verificar | H18: Verificar | I18: Verificar | J18: Verificar | K18: Verificar | L18: Verificar | M18: Verificar | N18: Verificar | O18: Verificar | P18: Verificar | Q18: No | R18: Pendiente
A19: TIS003 | B19: Tisana 3 · Manzanilla & melisa | C19: Verificar | D19: Verificar | E19: Verificar | F19: Verificar | G19: Verificar | H19: Verificar | I19: Verificar | J19: Verificar | K19: Verificar | L19: Verificar | M19: Verificar | N19: Verificar | O19: Verificar | P19: Verificar | Q19: No | R19: Pendiente
A20: BLE001 | B20: Del bosque | C20: Verificar | D20: Verificar | E20: Verificar | F20: Verificar | G20: Verificar | H20: Verificar | I20: Verificar | J20: Verificar | K20: Verificar | L20: Verificar | M20: Verificar | N20: Verificar | O20: Verificar | P20: Verificar | Q20: Sí | R20: Pendiente
A21: BLE002 | B21: Detox | C21: Verificar | D21: Verificar | E21: Verificar | F21: Verificar | G21: Verificar | H21: Verificar | I21: Verificar | J21: Verificar | K21: Verificar | L21: Verificar | M21: Verificar | N21: Verificar | O21: Verificar | P21: Verificar | Q21: Sí | R21: Pendiente
A22: BLE003 | B22: Dorado | C22: Verificar | D22: Verificar | E22: Verificar | F22: Verificar | G22: Verificar | H22: Verificar | I22: Verificar | J22: Verificar | K22: Verificar | L22: Verificar | M22: Verificar | N22: Verificar | O22: Verificar | P22: Verificar | Q22: Sí | R22: Pendiente
A23: BLE004 | B23: Love | C23: Verificar | D23: Verificar | E23: Verificar | F23: Verificar | G23: Verificar | H23: Verificar | I23: Verificar | J23: Verificar | K23: Verificar | L23: Verificar | M23: Verificar | N23: Verificar | O23: Verificar | P23: Verificar | Q23: Sí | R23: Pendiente
A24: ESP001 | B24: Submarino | C24: Verificar | D24: Verificar | E24: Verificar | F24: Verificar | G24: Verificar | H24: Verificar | I24: Verificar | J24: Verificar | K24: Verificar | L24: Verificar | M24: Verificar | N24: Verificar | O24: Verificar | P24: Verificar | Q24: Verificar | R24: Pendiente
A25: ESP002 | B25: Leche dorada | C25: Verificar | D25: Verificar | E25: Verificar | F25: Verificar | G25: Verificar | H25: Verificar | I25: Verificar | J25: Verificar | K25: Verificar | L25: Verificar | M25: Verificar | N25: Verificar | O25: Verificar | P25: Verificar | Q25: Verificar | R25: Pendiente
A26: CCL001 | B26: Americano | C26: Verificar | D26: Verificar | E26: Verificar | F26: Verificar | G26: Verificar | H26: Verificar | I26: Verificar | J26: Verificar | K26: Verificar | L26: Verificar | M26: Verificar | N26: Verificar | O26: Verificar | P26: Verificar | Q26: Sí | R26: Pendiente
A27: CCL002 | B27: Cortado | C27: Verificar | D27: Verificar | E27: Verificar | F27: Verificar | G27: Verificar | H27: Verificar | I27: Verificar | J27: Verificar | K27: Verificar | L27: Verificar | M27: Verificar | N27: Verificar | O27: Verificar | P27: Verificar | Q27: Sí | R27: Pendiente
... A35: CFR003 | B35: Frappé de dulce de leche | C35: Verificar | D35: Verificar | E35: Verificar | F35: Verificar | G35: Verificar | H35: Verificar | I35: Verificar | J35: Verificar | K35: Verificar | L35: Verificar | M35: Verificar | N35: Verificar | O35: Verificar | P35: Verificar | Q35: Sí | R35: Pendiente
A36: BYJ001 | B36: Batido de banana | C36: Verificar | D36: Verificar | E36: Verificar | F36: Verificar | G36: Verificar | H36: Verificar | I36: Verificar | J36: Verificar | K36: Verificar | L36: Verificar | M36: Verificar | N36: Verificar | O36: Verificar | P36: Verificar | Q36: Verificar | R36: Pendiente | S36: Confirmar si la base contiene leche.
A37: BYJ002 | B37: Batido de frutos rojos | C37: Verificar | D37: Verificar | E37: Verificar | F37: Verificar | G37: Verificar | H37: Verificar | I37: Verificar | J37: Verificar | K37: Verificar | L37: Verificar | M37: Verificar | N37: Verificar | O37: Verificar | P37: Verificar | Q37: Verificar | R37: Pendiente
A38: BYJ003 | B38: Limonada detox | C38: Verificar | D38: Verificar | E38: Verificar | F38: Verificar | G38: Verificar | H38: Verificar | I38: Verificar | J38: Verificar | K38: Verificar | L38: Verificar | M38: Verificar | N38: Verificar | O38: Verificar | P38: Verificar | Q38: Verificar | R38: Pendiente
A39: BYJ004 | B39: Limonada Jamaica | C39: Verificar | D39: Verificar | E39: Verificar | F39: Verificar | G39: Verificar | H39: Verificar | I39: Verificar | J39: Verificar | K39: Verificar | L39: Verificar | M39: Verificar | N39: Verificar | O39: Verificar | P39: Verificar | Q39: Verificar | R39: Pendiente
A40: BYJ005 | B40: Jugo de naranja | C40: Verificar | D40: Verificar | E40: Verificar | F40: Verificar | G40: Verificar | H40: Verificar | I40: Verificar | J40: Verificar | K40: Verificar | L40: Verificar | M40: Verificar | N40: Verificar | O40: Verificar | P40: Verificar | Q40: Verificar | R40: Pendiente
A41: BYJ006 | B41: Tropical | C41: Verificar | D41: Verificar | E41: Verificar | F41: Verificar | G41: Verificar | H41: Verificar | I41: Verificar | J41: Verificar | K41: Verificar | L41: Verificar | M41: Verificar | N41: Verificar | O41: Verificar | P41: Verificar | Q41: Verificar | R41: Pendiente
A42: ADI001 | B42: Leche vegetal | C42: Verificar | D42: Verificar | E42: Verificar | F42: Verificar | G42: Verificar | H42: Verificar | I42: Verificar | J42: Verificar | K42: Verificar | L42: Verificar | M42: Verificar | N42: Verificar | O42: Verificar | P42: Verificar | Q42: Verificar | R42: Pendiente
A43: ADI002 | B43: Leche sin lactosa | C43: Verificar | D43: Verificar | E43: Verificar | F43: Verificar | G43: Verificar | H43: Verificar | I43: Verificar | J43: Verificar | K43: Verificar | L43: Verificar | M43: Verificar | N43: Verificar | O43: Verificar | P43: Verificar | Q43: Verificar | R43: Pendiente
A44: STC001 | B44: Postres sin TACC | C44: Verificar | D44: Verificar | E44: Sí | F44: Verificar | G44: Verificar | H44: Verificar | I44: Verificar | J44: Verificar | K44: Verificar | L44: Verificar | M44: Verificar | N44: Verificar | O44: Verificar | P44: Verificar | Q44: Verificar | R44: Pendiente | S44: Producto tercerizado: validar certificación vigente, proveedor, almacenamiento, utensilios y riesgo de contaminación cruzada.
A45: STC002 | B45: Pasta frola sin TACC | C45: Verificar | D45: Verificar | E45: Sí | F45: Verificar | G45: Verificar | H45: Verificar | I45: Verificar | J45: Verificar | K45: Verificar | L45: Verificar | M45: Verificar | N45: Verificar | O45: Verificar | P45: Verificar | Q45: Verificar | R45: Pendiente | S45: Producto tercerizado: validar certificación vigente, proveedor, almacenamiento, utensilios y riesgo de contaminación cruzada.
A46: STC003 | B46: Tarta de coco y dulce de leche sin TACC | C46: Verificar | D46: Verificar | E46: Sí | F46: Verificar | G46: Verificar | H46: Verificar | I46: Verificar | J46: Verificar | K46: Verificar | L46: Verificar | M46: Verificar | N46: Verificar | O46: Verificar | P46: Verificar | Q46: Verificar | R46: Pendiente | S46: Producto tercerizado: validar certificación vigente, proveedor, almacenamiento, utensilios y riesgo de contaminación cruzada.
A47: STC004 | B47: Alfacookie sin TACC | C47: Verificar | D47: Verificar | E47: Sí | F47: Verificar | G47: Verificar | H47: Verificar | I47: Verificar | J47: Verificar | K47: Verificar | L47: Verificar | M47: Verificar | N47: Verificar | O47: Verificar | P47: Verificar | Q47: Verificar | R47: Pendiente | S47: Producto tercerizado: validar certificación vigente, proveedor, almacenamiento, utensilios y riesgo de contaminación cruzada.
A48: TYT001 | B48: Torta Amelí | C48: Verificar | D48: Verificar | E48: Verificar | F48: Verificar | G48: Verificar | H48: Verificar | I48: Verificar | J48: Verificar | K48: Verificar | L48: Verificar | M48: Verificar | N48: Verificar | O48: Verificar | P48: Verificar | Q48: Verificar | R48: Pendiente
A49: TYT002 | B49: Marquise | C49: Verificar | D49: Verificar | E49: Verificar | F49: Verificar | G49: Verificar | H49: Verificar | I49: Verificar | J49: Verificar | K49: Verificar | L49: Verificar | M49: Verificar | N49: Verificar | O49: Verificar | P49: Verificar | Q49: Verificar | R49: Pendiente
A50: TYT003 | B50: Cheesecake de frutos rojos | C50: Verificar | D50: Verificar | E50: Verificar | F50: Verificar | G50: Verificar | H50: Verificar | I50: Verificar | J50: Verificar | K50: Verificar | L50: Verificar | M50: Verificar | N50: Verificar | O50: Verificar | P50: Verificar | Q50: Verificar | R50: Pendiente
A51: TYT004 | B51: Red velvet | C51: Verificar | D51: Verificar | E51: Verificar | F51: Verificar | G51: Verificar | H51: Verificar | I51: Verificar | J51: Verificar | K51: Verificar | L51: Verificar | M51: Verificar | N51: Verificar | O51: Verificar | P51: Verificar | Q51: Verificar | R51: Pendiente
A52: TYT005 | B52: Key lime pie | C52: Verificar | D52: Verificar | E52: Verificar | F52: Verificar | G52: Verificar | H52: Verificar | I52: Verificar | J52: Verificar | K52: Verificar | L52: Verificar | M52: Verificar | N52: Verificar | O52: Verificar | P52: Verificar | Q52: Verificar | R52: Pendiente
A53: TYT006 | B53: Sablée de almendras | C53: Verificar | D53: Verificar | E53: Verificar | F53: Verificar | G53: Verificar | H53: Verificar | I53: Verificar | J53: Verificar | K53: Verificar | L53: Verificar | M53: Verificar | N53: Verificar | O53: Verificar | P53: Verificar | Q53: Verificar | R53: Pendiente
A54: TYT007 | B54: Franuí del bosque | C54: Verificar | D54: Verificar | E54: Verificar | F54: Verificar | G54: Verificar | H54: Verificar | I54: Verificar | J54: Verificar | K54: Verificar | L54: Verificar | M54: Verificar | N54: Verificar | O54: Verificar | P54: Verificar | Q54: Verificar | R54: Pendiente
A55: SAT001 | B55: Bagel | C55: Verificar | D55: Verificar | E55: Verificar | F55: Verificar | G55: Verificar | H55: Verificar | I55: Verificar | J55: Verificar | K55: Verificar | L55: Verificar | M55: Verificar | N55: Verificar | O55: Verificar | P55: Verificar | Q55: Verificar | R55: Pendiente
A56: SAT002 | B56: Tostado de jamón y queso | C56: Verificar | D56: Verificar | E56: Verificar | F56: Verificar | G56: Verificar | H56: Verificar | I56: Verificar | J56: Verificar | K56: Verificar | L56: Verificar | M56: Verificar | N56: Verificar | O56: Verificar | P56: Verificar | Q56: Verificar | R56: Pendiente
A57: SAT003 | B57: Tostón Amelí | C57: Verificar | D57: Verificar | E57: Verificar | F57: Verificar | G57: Verificar | H57: Verificar | I57: Verificar | J57: Verificar | K57: Verificar | L57: Verificar | M57: Verificar | N57: Verificar | O57: Verificar | P57: Verificar | Q57: Verificar | R57: Pendiente
A58: SAT004 | B58: Tostón de palta y huevo | C58: Verificar | D58: Verificar | E58: Verificar | F58: Verificar | G58: Verificar | H58: Verificar | I58: Verificar | J58: Verificar | K58: Verificar | L58: Verificar | M58: Verificar | N58: Verificar | O58: Verificar | P58: Verificar | Q58: Verificar | R58: Pendiente
A59: SAT005 | B59: Pistachero | C59: Verificar | D59: Verificar | E59: Verificar | F59: Verificar | G59: Verificar | H59: Verificar | I59: Verificar | J59: Verificar | K59: Verificar | L59: Verificar | M59: Verificar | N59: Verificar | O59: Verificar | P59: Verificar | Q59: Verificar | R59: Pendiente

Sheet 08_Personalización
A1: Personalización y adicionales
A2: Usar «Verificar» hasta definir reglas de cocina, recargos y disponibilidad. Las opciones visibles en el menú deben coincidir con la operación real.
A4: ID | B4: Producto ES-AR | C4: Admite cambios | D4: Leche vegetal | E4: Leche sin lactosa | F4: Extra espresso | G4: Extra crema | H4: Extra queso | I4: Extra palta | J4: Extra miel | K4: Extra dulce de leche | L4: Sin azúcar añadida | M4: Opción para llevar | N4: Observaciones
A5: DYM001 | B5: Avocado | C5: Verificar | D5: No | E5: No | F5: No | G5: Verificar | H5: Verificar | I5: Verificar | J5: Verificar | K5: Verificar | L5: No | M5: Verificar
A6: DYM002 | B6: Desayuno clásico | C6: Verificar | D6: No | E6: No | F6: No | G6: Verificar | H6: Verificar | I6: Verificar | J6: Verificar | K6: Verificar | L6: No | M6: Verificar
A7: DYM003 | B7: Desayuno mendocino | C7: Verificar | D7: No | E7: No | F7: No | G7: Verificar | H7: Verificar | I7: Verificar | J7: Verificar | K7: Verificar | L7: No | M7: Verificar
A8: DYM004 | B8: Desayuno saludable | C8: Verificar | D8: No | E8: No | F8: No | G8: Verificar | H8: Verificar | I8: Verificar | J8: Verificar | K8: Verificar | L8: No | M8: Verificar
A9: DEL001 | B9: Bowl de huevos | C9: Verificar | D9: No | E9: No | F9: No | G9: Verificar | H9: Verificar | I9: Verificar | J9: Verificar | K9: Verificar | L9: No | M9: Sí | N9: Confirmar receta y acompañamientos.
A10: DEL002 | B10: Bowl de frutas | C10: Verificar | D10: No | E10: No | F10: No | G10: Verificar | H10: Verificar | I10: Verificar | J10: Verificar | K10: Verificar | L10: No | M10: Sí
A11: DEL003 | B11: Chipá | C11: Verificar | D11: No | E11: No | F11: No | G11: Verificar | H11: Verificar | I11: Verificar | J11: Verificar | K11: Verificar | L11: No | M11: Sí
A12: DEL004 | B12: Medialunas | C12: Verificar | D12: No | E12: No | F12: No | G12: Verificar | H12: Verificar | I12: Verificar | J12: Verificar | K12: Verificar | L12: No | M12: Sí
A13: DEL005 | B13: Mini budines | C13: Verificar | D13: No | E13: No | F13: No | G13: Verificar | H13: Verificar | I13: Verificar | J13: Verificar | K13: Verificar | L13: No | M13: Sí | N13: Los ingredientes varían según el sabor.
A14: DEL006 | B14: Raspaditas mendocinas | C14: Verificar | D14: No | E14: No | F14: No | G14: Verificar | H14: Verificar | I14: Verificar | J14: Verificar | K14: Verificar | L14: No | M14: Sí
A15: DEL007 | B15: Smoothie bowl | C15: Verificar | D15: No | E15: No | F15: No | G15: Verificar | H15: Verificar | I15: Verificar | J15: Verificar | K15: Verificar | L15: No | M15: Sí | N15: Confirmar ingredientes, toppings y base líquida.
A16: TEH001 | B16: Selección de té en hebras | C16: Sí | D16: No | E16: No | F16: No | G16: Verificar | H16: Verificar | I16: Verificar | J16: Verificar | K16: Verificar | L16: Verificar | M16: Sí
A17: TIS001 | B17: Tisana 1 · Cedrón & lavanda | C17: Sí | D17: No | E17: No | F17: No | G17: Verificar | H17: Verificar | I17: Verificar | J17: Verificar | K17: Verificar | L17: Verificar | M17: Sí
A18: TIS002 | B18: Tisana 2 · Limón & menta | C18: Sí | D18: No | E18: No | F18: No | G18: Verificar | H18: Verificar | I18: Verificar | J18: Verificar | K18: Verificar | L18: Verificar | M18: Sí
A19: TIS003 | B19: Tisana 3 · Manzanilla & melisa | C19: Sí | D19: No | E19: No | F19: No | G19: Verificar | H19: Verificar | I19: Verificar | J19: Verificar | K19: Verificar | L19: Verificar | M19: Sí
A20: BLE001 | B20: Del bosque | C20: Sí | D20: No | E20: No | F20: No | G20: Verificar | H20: Verificar | I20: Verificar | J20: Verificar | K20: Verificar | L20: Verificar | M20: Sí
A21: BLE002 | B21: Detox | C21: Sí | D21: No | E21: No | F21: No | G21: Verificar | H21: Verificar | I21: Verificar | J21: Verificar | K21: Verificar | L21: Verificar | M21: Sí
A22: BLE003 | B22: Dorado | C22: Sí | D22: No | E22: No | F22: No | G22: Verificar | H22: Verificar | I22: Verificar | J22: Verificar | K22: Verificar | L22: Verificar | M22: Sí
A23: BLE004 | B23: Love | C23: Sí | D23: No | E23: No | F23: No | G23: Verificar | H23: Verificar | I23: Verificar | J23: Verificar | K23: Verificar | L23: Verificar | M23: Sí
A24: ESP001 | B24: Submarino | C24: Sí | D24: Sí | E24: Sí | F24: No | G24: Verificar | H24: Verificar | I24: Verificar | J24: Verificar | K24: Verificar | L24: Verificar | M24: Sí
A25: ESP002 | B25: Leche dorada | C25: Sí | D25: Sí | E25: Sí | F25: No | G25: Verificar | H25: Verificar | I25: Verificar | J25: Verificar | K25: Verificar | L25: Verificar | M25: Sí
A26: CCL001 | B26: Americano | C26: Sí | D26: No | E26: No | F26: Sí | G26: Verificar | H26: Verificar | I26: Verificar | J26: Verificar | K26: Verificar | L26: Verificar | M26: Sí
A27: CCL002 | B27: Cortado | C27: Sí | D27: Sí | E27: Sí | F27: Sí | G27: Verificar | H27: Verificar | I27: Verificar | J27: Verificar | K27: Verificar | L27: Verificar | M27: Sí
... A35: CFR003 | B35: Frappé de dulce de leche | C35: Sí | D35: Sí | E35: Sí | F35: Sí | G35: Verificar | H35: Verificar | I35: Verificar | J35: Verificar | K35: Verificar | L35: Verificar | M35: Sí
A36: BYJ001 | B36: Batido de banana | C36: Sí | D36: No | E36: No | F36: No | G36: Verificar | H36: Verificar | I36: Verificar | J36: Verificar | K36: Verificar | L36: Verificar | M36: Sí | N36: Confirmar si la base contiene leche.
A37: BYJ002 | B37: Batido de frutos rojos | C37: Sí | D37: No | E37: No | F37: No | G37: Verificar | H37: Verificar | I37: Verificar | J37: Verificar | K37: Verificar | L37: Verificar | M37: Sí
A38: BYJ003 | B38: Limonada detox | C38: Sí | D38: No | E38: No | F38: No | G38: Verificar | H38: Verificar | I38: Verificar | J38: Verificar | K38: Verificar | L38: Verificar | M38: Sí
A39: BYJ004 | B39: Limonada Jamaica | C39: Sí | D39: No | E39: No | F39: No | G39: Verificar | H39: Verificar | I39: Verificar | J39: Verificar | K39: Verificar | L39: Verificar | M39: Sí
A40: BYJ005 | B40: Jugo de naranja | C40: Sí | D40: No | E40: No | F40: No | G40: Verificar | H40: Verificar | I40: Verificar | J40: Verificar | K40: Verificar | L40: Verificar | M40: Sí
A41: BYJ006 | B41: Tropical | C41: Sí | D41: No | E41: No | F41: No | G41: Verificar | H41: Verificar | I41: Verificar | J41: Verificar | K41: Verificar | L41: Verificar | M41: Sí
A42: ADI001 | B42: Leche vegetal | C42: Verificar | D42: No | E42: No | F42: No | G42: Verificar | H42: Verificar | I42: Verificar | J42: Verificar | K42: Verificar | L42: No | M42: Sí
A43: ADI002 | B43: Leche sin lactosa | C43: Verificar | D43: No | E43: No | F43: No | G43: Verificar | H43: Verificar | I43: Verificar | J43: Verificar | K43: Verificar | L43: No | M43: Sí
A44: STC001 | B44: Postres sin TACC | C44: Verificar | D44: No | E44: No | F44: No | G44: Verificar | H44: Verificar | I44: Verificar | J44: Verificar | K44: Verificar | L44: No | M44: Sí | N44: Validar certificación, proveedor y riesgo de contaminación cruzada.
A45: STC002 | B45: Pasta frola sin TACC | C45: Verificar | D45: No | E45: No | F45: No | G45: Verificar | H45: Verificar | I45: Verificar | J45: Verificar | K45: Verificar | L45: No | M45: Sí | N45: Validar certificación, proveedor y riesgo de contaminación cruzada.
A46: STC003 | B46: Tarta de coco y dulce de leche sin TACC | C46: Verificar | D46: No | E46: No | F46: No | G46: Verificar | H46: Verificar | I46: Verificar | J46: Verificar | K46: Verificar | L46: No | M46: Sí | N46: Validar certificación, proveedor y riesgo de contaminación cruzada.
A47: STC004 | B47: Alfacookie sin TACC | C47: Verificar | D47: No | E47: No | F47: No | G47: Verificar | H47: Verificar | I47: Verificar | J47: Verificar | K47: Verificar | L47: No | M47: Sí | N47: Validar certificación, proveedor y riesgo de contaminación cruzada.
A48: TYT001 | B48: Torta Amelí | C48: Verificar | D48: No | E48: No | F48: No | G48: Verificar | H48: Verificar | I48: Verificar | J48: Verificar | K48: Verificar | L48: No | M48: Sí
A49: TYT002 | B49: Marquise | C49: Verificar | D49: No | E49: No | F49: No | G49: Verificar | H49: Verificar | I49: Verificar | J49: Verificar | K49: Verificar | L49: No | M49: Sí
A50: TYT003 | B50: Cheesecake de frutos rojos | C50: Verificar | D50: No | E50: No | F50: No | G50: Verificar | H50: Verificar | I50: Verificar | J50: Verificar | K50: Verificar | L50: No | M50: Sí
A51: TYT004 | B51: Red velvet | C51: Verificar | D51: No | E51: No | F51: No | G51: Verificar | H51: Verificar | I51: Verificar | J51: Verificar | K51: Verificar | L51: No | M51: Sí
A52: TYT005 | B52: Key lime pie | C52: Verificar | D52: No | E52: No | F52: No | G52: Verificar | H52: Verificar | I52: Verificar | J52: Verificar | K52: Verificar | L52: No | M52: Sí
A53: TYT006 | B53: Sablée de almendras | C53: Verificar | D53: No | E53: No | F53: No | G53: Verificar | H53: Verificar | I53: Verificar | J53: Verificar | K53: Verificar | L53: No | M53: Sí
A54: TYT007 | B54: Franuí del bosque | C54: Verificar | D54: No | E54: No | F54: No | G54: Verificar | H54: Verificar | I54: Verificar | J54: Verificar | K54: Verificar | L54: No | M54: Sí
A55: SAT001 | B55: Bagel | C55: Verificar | D55: No | E55: No | F55: No | G55: Verificar | H55: Verificar | I55: Verificar | J55: Verificar | K55: Verificar | L55: No | M55: Sí
A56: SAT002 | B56: Tostado de jamón y queso | C56: Verificar | D56: No | E56: No | F56: No | G56: Verificar | H56: Verificar | I56: Verificar | J56: Verificar | K56: Verificar | L56: No | M56: Sí
A57: SAT003 | B57: Tostón Amelí | C57: Verificar | D57: No | E57: No | F57: No | G57: Verificar | H57: Verificar | I57: Verificar | J57: Verificar | K57: Verificar | L57: No | M57: Sí
A58: SAT004 | B58: Tostón de palta y huevo | C58: Verificar | D58: No | E58: No | F58: No | G58: Verificar | H58: Verificar | I58: Verificar | J58: Verificar | K58: Verificar | L58: No | M58: Sí
A59: SAT005 | B59: Pistachero | C59: Verificar | D59: No | E59: No | F59: No | G59: Verificar | H59: Verificar | I59: Verificar | J59: Verificar | K59: Verificar | L59: No | M59: Sí

Sheet 09_Ingeniería_Menú
A1: Ingeniería de menú · Matriz Estrella / Caballo / Puzzle / Perro
A2: La clasificación se activa al cargar precio, costo y unidades vendidas. No sustituye el criterio de marca, disponibilidad ni complejidad operativa.
A4: ID | B4: Producto ES-AR | C4: Categoría | D4: Precio local | E4: Costo unitario | F4: Margen de contribución | G4: Margen % | H4: Unidades vendidas | I4: Popularidad en categoría | J4: Promedio ventas categoría | K4: Promedio margen categoría | L4: Clasificación | M4: Prioridad sugerida | N4: Etiqueta sugerida | O4: Decisión editorial | P4: Observaciones
A5: DYM001 | B5: Avocado | C5: Desayunos & Meriendas | D5: =IFERROR(INDEX(04_Precios!$D$5:$D$59,MATCH($A5,04_Precios!$A$5:$A$59,0)),"") -> 0 | E5: =IFERROR(INDEX(04_Precios!$H$5:$H$59,MATCH($A5,04_Precios!$A$5:$A$59,0)),"") -> 0 | F5: =IF(OR(D5="",E5=""),"",D5-E5) | G5: =IFERROR(F5/D5,"") | H5: =IFERROR(INDEX(12_Estadísticas!$C$5:$C$59,MATCH($A5,12_Estadísticas!$A$5:$A$59,0)),"") -> 0 | I5: =IFERROR(H5/SUMIF($C$5:$C$59,C5,$H$5:$H$59),"") | J5: =IFERROR(AVERAGEIF($C$5:$C$59,C5,$H$5:$H$59),"") -> 0 | K5: =IFERROR(AVERAGEIF($C$5:$C$59,C5,$F$5:$F$59),"") | L5: =IF(OR(D5="",E5="",H5=""),"Sin datos",IF(AND(H5>=J5,F5>=K5),"Estrella",IF(AND(H5>=J5,F5<K5),"Caballo de batalla",IF(AND(H5<J5,F5>=K5),"Incógnita","Perro")))) -> Sin datos | M5: =IF(L5="Estrella","Mantener visibilidad",IF(L5="Caballo de batalla","Optimizar margen",IF(L5="Puzzle","Aumentar visibilidad",IF(L5="Perro","Revisar continuidad","Esperar datos")))) -> Esperar datos | N5: =IF(L5="Estrella","Más pedido",IF(L5="Puzzle","Recomendado",IF(L5="Caballo de batalla","Clásico",IF(L5="Perro","",""))))
A6: DYM002 | B6: Desayuno clásico | C6: Desayunos & Meriendas | D6: =IFERROR(INDEX(04_Precios!$D$5:$D$59,MATCH($A6,04_Precios!$A$5:$A$59,0)),"") -> 0 | E6: =IFERROR(INDEX(04_Precios!$H$5:$H$59,MATCH($A6,04_Precios!$A$5:$A$59,0)),"") -> 0 | F6: =IF(OR(D6="",E6=""),"",D6-E6) | G6: =IFERROR(F6/D6,"") | H6: =IFERROR(INDEX(12_Estadísticas!$C$5:$C$59,MATCH($A6,12_Estadísticas!$A$5:$A$59,0)),"") -> 0 | I6: =IFERROR(H6/SUMIF($C$5:$C$59,C6,$H$5:$H$59),"") | J6: =IFERROR(AVERAGEIF($C$5:$C$59,C6,$H$5:$H$59),"") -> 0 | K6: =IFERROR(AVERAGEIF($C$5:$C$59,C6,$F$5:$F$59),"") | L6: =IF(OR(D6="",E6="",H6=""),"Sin datos",IF(AND(H6>=J6,F6>=K6),"Estrella",IF(AND(H6>=J6,F6<K6),"Caballo de batalla",IF(AND(H6<J6,F6>=K6),"Incógnita","Perro")))) -> Sin datos | M6: =IF(L6="Estrella","Mantener visibilidad",IF(L6="Caballo de batalla","Optimizar margen",IF(L6="Puzzle","Aumentar visibilidad",IF(L6="Perro","Revisar continuidad","Esperar datos")))) -> Esperar datos | N6: =IF(L6="Estrella","Más pedido",IF(L6="Puzzle","Recomendado",IF(L6="Caballo de batalla","Clásico",IF(L6="Perro","",""))))
A7: DYM003 | B7: Desayuno mendocino | C7: Desayunos & Meriendas | D7: =IFERROR(INDEX(04_Precios!$D$5:$D$59,MATCH($A7,04_Precios!$A$5:$A$59,0)),"") -> 0 | E7: =IFERROR(INDEX(04_Precios!$H$5:$H$59,MATCH($A7,04_Precios!$A$5:$A$59,0)),"") -> 0 | F7: =IF(OR(D7="",E7=""),"",D7-E7) | G7: =IFERROR(F7/D7,"") | H7: =IFERROR(INDEX(12_Estadísticas!$C$5:$C$59,MATCH($A7,12_Estadísticas!$A$5:$A$59,0)),"") -> 0 | I7: =IFERROR(H7/SUMIF($C$5:$C$59,C7,$H$5:$H$59),"") | J7: =IFERROR(AVERAGEIF($C$5:$C$59,C7,$H$5:$H$59),"") -> 0 | K7: =IFERROR(AVERAGEIF($C$5:$C$59,C7,$F$5:$F$59),"") | L7: =IF(OR(D7="",E7="",H7=""),"Sin datos",IF(AND(H7>=J7,F7>=K7),"Estrella",IF(AND(H7>=J7,F7<K7),"Caballo de batalla",IF(AND(H7<J7,F7>=K7),"Incógnita","Perro")))) -> Sin datos | M7: =IF(L7="Estrella","Mantener visibilidad",IF(L7="Caballo de batalla","Optimizar margen",IF(L7="Puzzle","Aumentar visibilidad",IF(L7="Perro","Revisar continuidad","Esperar datos")))) -> Esperar datos | N7: =IF(L7="Estrella","Más pedido",IF(L7="Puzzle","Recomendado",IF(L7="Caballo de batalla","Clásico",IF(L7="Perro","",""))))
A8: DYM004 | B8: Desayuno saludable | C8: Desayunos & Meriendas | D8: =IFERROR(INDEX(04_Precios!$D$5:$D$59,MATCH($A8,04_Precios!$A$5:$A$59,0)),"") -> 0 | E8: =IFERROR(INDEX(04_Precios!$H$5:$H$59,MATCH($A8,04_Precios!$A$5:$A$59,0)),"") -> 0 | F8: =IF(OR(D8="",E8=""),"",D8-E8) | G8: =IFERROR(F8/D8,"") | H8: =IFERROR(INDEX(12_Estadísticas!$C$5:$C$59,MATCH($A8,12_Estadísticas!$A$5:$A$59,0)),"") -> 0 | I8: =IFERROR(H8/SUMIF($C$5:$C$59,C8,$H$5:$H$59),"") | J8: =IFERROR(AVERAGEIF($C$5:$C$59,C8,$H$5:$H$59),"") -> 0 | K8: =IFERROR(AVERAGEIF($C$5:$C$59,C8,$F$5:$F$59),"") | L8: =IF(OR(D8="",E8="",H8=""),"Sin datos",IF(AND(H8>=J8,F8>=K8),"Estrella",IF(AND(H8>=J8,F8<K8),"Caballo de batalla",IF(AND(H8<J8,F8>=K8),"Incógnita","Perro")))) -> Sin datos | M8: =IF(L8="Estrella","Mantener visibilidad",IF(L8="Caballo de batalla","Optimizar margen",IF(L8="Puzzle","Aumentar visibilidad",IF(L8="Perro","Revisar continuidad","Esperar datos")))) -> Esperar datos | N8: =IF(L8="Estrella","Más pedido",IF(L8="Puzzle","Recomendado",IF(L8="Caballo de batalla","Clásico",IF(L8="Perro","",""))))
A9: DEL001 | B9: Bowl de huevos | C9: Delicias | D9: =IFERROR(INDEX(04_Precios!$D$5:$D$59,MATCH($A9,04_Precios!$A$5:$A$59,0)),"") -> 0 | E9: =IFERROR(INDEX(04_Precios!$H$5:$H$59,MATCH($A9,04_Precios!$A$5:$A$59,0)),"") -> 0 | F9: =IF(OR(D9="",E9=""),"",D9-E9) | G9: =IFERROR(F9/D9,"") | H9: =IFERROR(INDEX(12_Estadísticas!$C$5:$C$59,MATCH($A9,12_Estadísticas!$A$5:$A$59,0)),"") -> 0 | I9: =IFERROR(H9/SUMIF($C$5:$C$59,C9,$H$5:$H$59),"") | J9: =IFERROR(AVERAGEIF($C$5:$C$59,C9,$H$5:$H$59),"") -> 0 | K9: =IFERROR(AVERAGEIF($C$5:$C$59,C9,$F$5:$F$59),"") | L9: =IF(OR(D9="",E9="",H9=""),"Sin datos",IF(AND(H9>=J9,F9>=K9),"Estrella",IF(AND(H9>=J9,F9<K9),"Caballo de batalla",IF(AND(H9<J9,F9>=K9),"Incógnita","Perro")))) -> Sin datos | M9: =IF(L9="Estrella","Mantener visibilidad",IF(L9="Caballo de batalla","Optimizar margen",IF(L9="Puzzle","Aumentar visibilidad",IF(L9="Perro","Revisar continuidad","Esperar datos")))) -> Esperar datos | N9: =IF(L9="Estrella","Más pedido",IF(L9="Puzzle","Recomendado",IF(L9="Caballo de batalla","Clásico",IF(L9="Perro","",""))))
A10: DEL002 | B10: Bowl de frutas | C10: Delicias | D10: =IFERROR(INDEX(04_Precios!$D$5:$D$59,MATCH($A10,04_Precios!$A$5:$A$59,0)),"") -> 0 | E10: =IFERROR(INDEX(04_Precios!$H$5:$H$59,MATCH($A10,04_Precios!$A$5:$A$59,0)),"") -> 0 | F10: =IF(OR(D10="",E10=""),"",D10-E10) | G10: =IFERROR(F10/D10,"") | H10: =IFERROR(INDEX(12_Estadísticas!$C$5:$C$59,MATCH($A10,12_Estadísticas!$A$5:$A$59,0)),"") -> 0 | I10: =IFERROR(H10/SUMIF($C$5:$C$59,C10,$H$5:$H$59),"") | J10: =IFERROR(AVERAGEIF($C$5:$C$59,C10,$H$5:$H$59),"") -> 0 | K10: =IFERROR(AVERAGEIF($C$5:$C$59,C10,$F$5:$F$59),"") | L10: =IF(OR(D10="",E10="",H10=""),"Sin datos",IF(AND(H10>=J10,F10>=K10),"Estrella",IF(AND(H10>=J10,F10<K10),"Caballo de batalla",IF(AND(H10<J10,F10>=K10),"Incógnita","Perro")))) -> Sin datos | M10: =IF(L10="Estrella","Mantener visibilidad",IF(L10="Caballo de batalla","Optimizar margen",IF(L10="Puzzle","Aumentar visibilidad",IF(L10="Perro","Revisar continuidad","Esperar datos")))) -> Esperar datos | N10: =IF(L10="Estrella","Más pedido",IF(L10="Puzzle","Recomendado",IF(L10="Caballo de batalla","Clásico",IF(L10="Perro","",""))))
A11: DEL003 | B11: Chipá | C11: Delicias | D11: =IFERROR(INDEX(04_Precios!$D$5:$D$59,MATCH($A11,04_Precios!$A$5:$A$59,0)),"") -> 0 | E11: =IFERROR(INDEX(04_Precios!$H$5:$H$59,MATCH($A11,04_Precios!$A$5:$A$59,0)),"") -> 0 | F11: =IF(OR(D11="",E11=""),"",D11-E11) | G11: =IFERROR(F11/D11,"") | H11: =IFERROR(INDEX(12_Estadísticas!$C$5:$C$59,MATCH($A11,12_Estadísticas!$A$5:$A$59,0)),"") -> 0 | I11: =IFERROR(H11/SUMIF($C$5:$C$59,C11,$H$5:$H$59),"") | J11: =IFERROR(AVERAGEIF($C$5:$C$59,C11,$H$5:$H$59),"") -> 0 | K11: =IFERROR(AVERAGEIF($C$5:$C$59,C11,$F$5:$F$59),"") | L11: =IF(OR(D11="",E11="",H11=""),"Sin datos",IF(AND(H11>=J11,F11>=K11),"Estrella",IF(AND(H11>=J11,F11<K11),"Caballo de batalla",IF(AND(H11<J11,F11>=K11),"Incógnita","Perro")))) -> Sin datos | M11: =IF(L11="Estrella","Mantener visibilidad",IF(L11="Caballo de batalla","Optimizar margen",IF(L11="Puzzle","Aumentar visibilidad",IF(L11="Perro","Revisar continuidad","Esperar datos")))) -> Esperar datos | N11: =IF(L11="Estrella","Más pedido",IF(L11="Puzzle","Recomendado",IF(L11="Caballo de batalla","Clásico",IF(L11="Perro","",""))))
A12: DEL004 | B12: Medialunas | C12: Delicias | D12: =IFERROR(INDEX(04_Precios!$D$5:$D$59,MATCH($A12,04_Precios!$A$5:$A$59,0)),"") -> 0 | E12: =IFERROR(INDEX(04_Precios!$H$5:$H$59,MATCH($A12,04_Precios!$A$5:$A$59,0)),"") -> 0 | F12: =IF(OR(D12="",E12=""),"",D12-E12) | G12: =IFERROR(F12/D12,"") | H12: =IFERROR(INDEX(12_Estadísticas!$C$5:$C$59,MATCH($A12,12_Estadísticas!$A$5:$A$59,0)),"") -> 0 | I12: =IFERROR(H12/SUMIF($C$5:$C$59,C12,$H$5:$H$59),"") | J12: =IFERROR(AVERAGEIF($C$5:$C$59,C12,$H$5:$H$59),"") -> 0 | K12: =IFERROR(AVERAGEIF($C$5:$C$59,C12,$F$5:$F$59),"") | L12: =IF(OR(D12="",E12="",H12=""),"Sin datos",IF(AND(H12>=J12,F12>=K12),"Estrella",IF(AND(H12>=J12,F12<K12),"Caballo de batalla",IF(AND(H12<J12,F12>=K12),"Incógnita","Perro")))) -> Sin datos | M12: =IF(L12="Estrella","Mantener visibilidad",IF(L12="Caballo de batalla","Optimizar margen",IF(L12="Puzzle","Aumentar visibilidad",IF(L12="Perro","Revisar continuidad","Esperar datos")))) -> Esperar datos | N12: =IF(L12="Estrella","Más pedido",IF(L12="Puzzle","Recomendado",IF(L12="Caballo de batalla","Clásico",IF(L12="Perro","",""))))
A13: DEL005 | B13: Mini budines | C13: Delicias | D13: =IFERROR(INDEX(04_Precios!$D$5:$D$59,MATCH($A13,04_Precios!$A$5:$A$59,0)),"") -> 0 | E13: =IFERROR(INDEX(04_Precios!$H$5:$H$59,MATCH($A13,04_Precios!$A$5:$A$59,0)),"") -> 0 | F13: =IF(OR(D13="",E13=""),"",D13-E13) | G13: =IFERROR(F13/D13,"") | H13: =IFERROR(INDEX(12_Estadísticas!$C$5:$C$59,MATCH($A13,12_Estadísticas!$A$5:$A$59,0)),"") -> 0 | I13: =IFERROR(H13/SUMIF($C$5:$C$59,C13,$H$5:$H$59),"") | J13: =IFERROR(AVERAGEIF($C$5:$C$59,C13,$H$5:$H$59),"") -> 0 | K13: =IFERROR(AVERAGEIF($C$5:$C$59,C13,$F$5:$F$59),"") | L13: =IF(OR(D13="",E13="",H13=""),"Sin datos",IF(AND(H13>=J13,F13>=K13),"Estrella",IF(AND(H13>=J13,F13<K13),"Caballo de batalla",IF(AND(H13<J13,F13>=K13),"Incógnita","Perro")))) -> Sin datos | M13: =IF(L13="Estrella","Mantener visibilidad",IF(L13="Caballo de batalla","Optimizar margen",IF(L13="Puzzle","Aumentar visibilidad",IF(L13="Perro","Revisar continuidad","Esperar datos")))) -> Esperar datos | N13: =IF(L13="Estrella","Más pedido",IF(L13="Puzzle","Recomendado",IF(L13="Caballo de batalla","Clásico",IF(L13="Perro","",""))))
A14: DEL006 | B14: Raspaditas mendocinas | C14: Delicias | D14: =IFERROR(INDEX(04_Precios!$D$5:$D$59,MATCH($A14,04_Precios!$A$5:$A$59,0)),"") -> 0 | E14: =IFERROR(INDEX(04_Precios!$H$5:$H$59,MATCH($A14,04_Precios!$A$5:$A$59,0)),"") -> 0 | F14: =IF(OR(D14="",E14=""),"",D14-E14) | G14: =IFERROR(F14/D14,"") | H14: =IFERROR(INDEX(12_Estadísticas!$C$5:$C$59,MATCH($A14,12_Estadísticas!$A$5:$A$59,0)),"") -> 0 | I14: =IFERROR(H14/SUMIF($C$5:$C$59,C14,$H$5:$H$59),"") | J14: =IFERROR(AVERAGEIF($C$5:$C$59,C14,$H$5:$H$59),"") -> 0 | K14: =IFERROR(AVERAGEIF($C$5:$C$59,C14,$F$5:$F$59),"") | L14: =IF(OR(D14="",E14="",H14=""),"Sin datos",IF(AND(H14>=J14,F14>=K14),"Estrella",IF(AND(H14>=J14,F14<K14),"Caballo de batalla",IF(AND(H14<J14,F14>=K14),"Incógnita","Perro")))) -> Sin datos | M14: =IF(L14="Estrella","Mantener visibilidad",IF(L14="Caballo de batalla","Optimizar margen",IF(L14="Puzzle","Aumentar visibilidad",IF(L14="Perro","Revisar continuidad","Esperar datos")))) -> Esperar datos | N14: =IF(L14="Estrella","Más pedido",IF(L14="Puzzle","Recomendado",IF(L14="Caballo de batalla","Clásico",IF(L14="Perro","",""))))
A15: DEL007 | B15: Smoothie bowl | C15: Delicias | D15: =IFERROR(INDEX(04_Precios!$D$5:$D$59,MATCH($A15,04_Precios!$A$5:$A$59,0)),"") -> 0 | E15: =IFERROR(INDEX(04_Precios!$H$5:$H$59,MATCH($A15,04_Precios!$A$5:$A$59,0)),"") -> 0 | F15: =IF(OR(D15="",E15=""),"",D15-E15) | G15: =IFERROR(F15/D15,"") | H15: =IFERROR(INDEX(12_Estadísticas!$C$5:$C$59,MATCH($A15,12_Estadísticas!$A$5:$A$59,0)),"") -> 0 | I15: =IFERROR(H15/SUMIF($C$5:$C$59,C15,$H$5:$H$59),"") | J15: =IFERROR(AVERAGEIF($C$5:$C$59,C15,$H$5:$H$59),"") -> 0 | K15: =IFERROR(AVERAGEIF($C$5:$C$59,C15,$F$5:$F$59),"") | L15: =IF(OR(D15="",E15="",H15=""),"Sin datos",IF(AND(H15>=J15,F15>=K15),"Estrella",IF(AND(H15>=J15,F15<K15),"Caballo de batalla",IF(AND(H15<J15,F15>=K15),"Incógnita","Perro")))) -> Sin datos | M15: =IF(L15="Estrella","Mantener visibilidad",IF(L15="Caballo de batalla","Optimizar margen",IF(L15="Puzzle","Aumentar visibilidad",IF(L15="Perro","Revisar continuidad","Esperar datos")))) -> Esperar datos | N15: =IF(L15="Estrella","Más pedido",IF(L15="Puzzle","Recomendado",IF(L15="Caballo de batalla","Clásico",IF(L15="Perro","",""))))
A16: TEH001 | B16: Selección de té en hebras | C16: Té en Hebras | D16: =IFERROR(INDEX(04_Precios!$D$5:$D$59,MATCH($A16,04_Precios!$A$5:$A$59,0)),"") -> 0 | E16: =IFERROR(INDEX(04_Precios!$H$5:$H$59,MATCH($A16,04_Precios!$A$5:$A$59,0)),"") -> 0 | F16: =IF(OR(D16="",E16=""),"",D16-E16) | G16: =IFERROR(F16/D16,"") | H16: =IFERROR(INDEX(12_Estadísticas!$C$5:$C$59,MATCH($A16,12_Estadísticas!$A$5:$A$59,0)),"") -> 0 | I16: =IFERROR(H16/SUMIF($C$5:$C$59,C16,$H$5:$H$59),"") | J16: =IFERROR(AVERAGEIF($C$5:$C$59,C16,$H$5:$H$59),"") -> 0 | K16: =IFERROR(AVERAGEIF($C$5:$C$59,C16,$F$5:$F$59),"") | L16: =IF(OR(D16="",E16="",H16=""),"Sin datos",IF(AND(H16>=J16,F16>=K16),"Estrella",IF(AND(H16>=J16,F16<K16),"Caballo de batalla",IF(AND(H16<J16,F16>=K16),"Incógnita","Perro")))) -> Sin datos | M16: =IF(L16="Estrella","Mantener visibilidad",IF(L16="Caballo de batalla","Optimizar margen",IF(L16="Puzzle","Aumentar visibilidad",IF(L16="Perro","Revisar continuidad","Esperar datos")))) -> Esperar datos | N16: =IF(L16="Estrella","Más pedido",IF(L16="Puzzle","Recomendado",IF(L16="Caballo de batalla","Clásico",IF(L16="Perro","",""))))
... A59: SAT005 | B59: Pistachero | C59: Sándwiches & Tostones | D59: =IFERROR(INDEX(04_Precios!$D$5:$D$59,MATCH($A59,04_Precios!$A$5:$A$59,0)),"") -> 0 | E59: =IFERROR(INDEX(04_Precios!$H$5:$H$59,MATCH($A59,04_Precios!$A$5:$A$59,0)),"") -> 0 | F59: =IF(OR(D59="",E59=""),"",D59-E59) | G59: =IFERROR(F59/D59,"") | H59: =IFERROR(INDEX(12_Estadísticas!$C$5:$C$59,MATCH($A59,12_Estadísticas!$A$5:$A$59,0)),"") -> 0 | I59: =IFERROR(H59/SUMIF($C$5:$C$59,C59,$H$5:$H$59),"") | J59: =IFERROR(AVERAGEIF($C$5:$C$59,C59,$H$5:$H$59),"") -> 0 | K59: =IFERROR(AVERAGEIF($C$5:$C$59,C59,$F$5:$F$59),"") | L59: =IF(OR(D59="",E59="",H59=""),"Sin datos",IF(AND(H59>=J59,F59>=K59),"Estrella",IF(AND(H59>=J59,F59<K59),"Caballo de batalla",IF(AND(H59<J59,F59>=K59),"Incógnita","Perro")))) -> Sin datos | M59: =IF(L59="Estrella","Mantener visibilidad",IF(L59="Caballo de batalla","Optimizar margen",IF(L59="Puzzle","Aumentar visibilidad",IF(L59="Perro","Revisar continuidad","Esperar datos")))) -> Esperar datos | N59: =IF(L59="Estrella","Más pedido",IF(L59="Puzzle","Recomendado",IF(L59="Caballo de batalla","Clásico",IF(L59="Perro","",""))))

Sheet 10_Multimedia_SEO
A1: Multimedia, accesibilidad y SEO multilingüe
A2: Completar URLs de imágenes y video. Los textos alternativos, slugs y metadatos ya están localizados para cada idioma.
A4: ID | B4: Producto ES-AR | C4: URL imagen principal | D4: URL imagen 2 | E4: URL video | F4: Alt text ES | G4: Alt text EN | H4: Alt text PT | I4: Alt text FR | J4: Alt text IT | K4: Slug ES | L4: Slug EN | M4: Slug PT | N4: Slug FR | O4: Slug IT | P4: Meta title ES | Q4: Meta title EN | R4: Meta title PT | S4: Meta title FR | T4: Meta title IT | U4: Meta description ES | V4: Meta description EN | W4: Meta description PT | X4: Meta description FR | Y4: Meta description IT
A5: DYM001 | B5: Avocado | F5: Avocado de Amelí Casa de Té & Brunch. | G5: Avocado Breakfast at Amelí Casa de Té & Brunch. | H5: Café da manhã com abacate da Amelí Casa de Té & Brunch. | I5: Petit-déjeuner à l’avocat chez Amelí Casa de Té & Brunch. | J5: Colazione con avocado da Amelí Casa de Té & Brunch. | K5: avocado | L5: avocado-breakfast | M5: cafe-da-manha-com-abacate | N5: petit-dejeuner-a-l-avocat | O5: colazione-con-avocado | P5: Avocado | Amelí | Q5: Avocado Breakfast | Amelí | R5: Café da manhã com abacate | Amelí | S5: Petit-déjeuner à l’avocat | Amelí | T5: Colazione con avocado | Amelí | U5: Bowl de huevos revueltos y palta, acompañado de dos tostadas, queso crema, café o té y un vaso pequeño de jugo de naranja. Disponible en Amelí, Malargüe… | V5: A bowl of scrambled eggs and avocado, served with two slices of toast, cream cheese, coffee or tea, and a small glass of orange juice. Available at Amelí… | W5: Bowl de ovos mexidos com abacate, acompanhado de duas torradas, cream cheese, café ou chá e um pequeno copo de suco de laranja. Disponível na Amelí, em… | X5: Bol d’œufs brouillés et d’avocat, accompagné de deux toasts, de fromage frais, d’un café ou d’un thé et d’un petit verre de jus d’orange. À découvrir chez… | Y5: Bowl con uova strapazzate e avocado, accompagnato da due fette di pane tostato, formaggio spalmabile, caffè o tè e un piccolo bicchiere di succo…
A6: DYM002 | B6: Desayuno clásico | F6: Desayuno clásico de Amelí Casa de Té & Brunch. | G6: Classic Breakfast at Amelí Casa de Té & Brunch. | H6: Café da manhã clássico da Amelí Casa de Té & Brunch. | I6: Petit-déjeuner classique chez Amelí Casa de Té & Brunch. | J6: Colazione classica da Amelí Casa de Té & Brunch. | K6: desayuno-clasico | L6: classic-breakfast | M6: cafe-da-manha-classico | N6: petit-dejeuner-classique | O6: colazione-classica | P6: Desayuno clásico | Amelí | Q6: Classic Breakfast | Amelí | R6: Café da manhã clássico | Amelí | S6: Petit-déjeuner classique | Amelí | T6: Colazione classica | Amelí | U6: Dos tostadas con queso crema y mermelada, acompañadas de café o té y un vaso pequeño de jugo de naranja. Disponible en Amelí, Malargüe, Mendoza. | V6: Two slices of toast with cream cheese and jam, served with coffee or tea and a small glass of orange juice. Available at Amelí in Malargüe, Mendoza. | W6: Duas torradas com cream cheese e geleia, acompanhadas de café ou chá e um pequeno copo de suco de laranja. Disponível na Amelí, em Malargüe, Mendoza. | X6: Deux toasts avec fromage frais et confiture, accompagnés d’un café ou d’un thé et d’un petit verre de jus d’orange. À découvrir chez Amelí, à Malargüe… | Y6: Due fette di pane tostato con formaggio spalmabile e confettura, accompagnate da caffè o tè e da un piccolo bicchiere di succo d’arancia. Disponibile da…
A7: DYM003 | B7: Desayuno mendocino | F7: Desayuno mendocino de Amelí Casa de Té & Brunch. | G7: Mendoza Breakfast at Amelí Casa de Té & Brunch. | H7: Café da manhã mendocino da Amelí Casa de Té & Brunch. | I7: Petit-déjeuner mendocin chez Amelí Casa de Té & Brunch. | J7: Colazione mendocina da Amelí Casa de Té & Brunch. | K7: desayuno-mendocino | L7: mendoza-breakfast | M7: cafe-da-manha-mendocino | N7: petit-dejeuner-mendocin | O7: colazione-mendocina | P7: Desayuno mendocino | Amelí | Q7: Mendoza Breakfast | Amelí | R7: Café da manhã mendocino | Amelí | S7: Petit-déjeuner mendocin | Amelí | T7: Colazione mendocina | Amelí | U7: Dos raspaditas mendocinas, acompañadas de café o té y un vaso pequeño de jugo de naranja. Disponible en Amelí, Malargüe, Mendoza. | V7: Two traditional Mendoza raspaditas, served with coffee or tea and a small glass of orange juice. Available at Amelí in Malargüe, Mendoza. | W7: Duas raspaditas tradicionais de Mendoza, acompanhadas de café ou chá e um pequeno copo de suco de laranja. Disponível na Amelí, em Malargüe, Mendoza. | X7: Deux raspaditas traditionnelles de Mendoza, accompagnées d’un café ou d’un thé et d’un petit verre de jus d’orange. À découvrir chez Amelí, à Malargüe… | Y7: Due raspaditas tradizionali di Mendoza, accompagnate da caffè o tè e da un piccolo bicchiere di succo d’arancia. Disponibile da Amelí, a Malargüe, Mendoza.
A8: DYM004 | B8: Desayuno saludable | F8: Desayuno saludable de Amelí Casa de Té & Brunch. | G8: Healthy Breakfast at Amelí Casa de Té & Brunch. | H8: Café da manhã saudável da Amelí Casa de Té & Brunch. | I8: Petit-déjeuner équilibré chez Amelí Casa de Té & Brunch. | J8: Colazione salutare da Amelí Casa de Té & Brunch. | K8: desayuno-saludable | L8: healthy-breakfast | M8: cafe-da-manha-saudavel | N8: petit-dejeuner-equilibre | O8: colazione-salutare | P8: Desayuno saludable | Amelí | Q8: Healthy Breakfast | Amelí | R8: Café da manhã saudável | Amelí | S8: Petit-déjeuner équilibré | Amelí | T8: Colazione salutare | Amelí | U8: Yogur con frutas de estación, granola, frutos secos, miel y coco, acompañado de café o té y un vaso pequeño de jugo de naranja. Disponible en Amelí… | V8: Yoghurt with seasonal fruit, granola, nuts, honey and coconut, served with coffee or tea and a small glass of orange juice. Available at Amelí in… | W8: Iogurte com frutas da estação, granola, castanhas, mel e coco, acompanhado de café ou chá e um pequeno copo de suco de laranja. Disponível na Amelí, em… | X8: Yaourt aux fruits de saison, granola, fruits à coque, miel et noix de coco, accompagné d’un café ou d’un thé et d’un petit verre de jus d’orange. À… | Y8: Yogurt con frutta di stagione, granola, frutta secca, miele e cocco, accompagnato da caffè o tè e da un piccolo bicchiere di succo d’arancia. Disponibile…
A9: DEL001 | B9: Bowl de huevos | F9: Bowl de huevos de Amelí Casa de Té & Brunch. | G9: Egg Bowl at Amelí Casa de Té & Brunch. | H9: Bowl de ovos da Amelí Casa de Té & Brunch. | I9: Bowl d’œufs chez Amelí Casa de Té & Brunch. | J9: Bowl di uova da Amelí Casa de Té & Brunch. | K9: bowl-de-huevos | L9: egg-bowl | M9: bowl-de-ovos | N9: bowl-d-ufs | O9: bowl-di-uova | P9: Bowl de huevos | Amelí | Q9: Egg Bowl | Amelí | R9: Bowl de ovos | Amelí | S9: Bowl d’œufs | Amelí | T9: Bowl di uova | Amelí | U9: Huevos preparados al momento y servidos en bowl. Consultar los acompañamientos disponibles. Disponible en Amelí, Malargüe, Mendoza. | V9: Eggs cooked to order and served in a bowl. Please ask about the available accompaniments. Available at Amelí in Malargüe, Mendoza. | W9: Ovos preparados na hora e servidos em bowl. Consulte os acompanhamentos disponíveis. Disponível na Amelí, em Malargüe, Mendoza. | X9: Œufs préparés à la demande et servis dans un bol. Merci de consulter les accompagnements disponibles. À découvrir chez Amelí, à Malargüe, Mendoza. | Y9: Uova preparate al momento e servite in bowl. Chiedere quali accompagnamenti sono disponibili. Disponibile da Amelí, a Malargüe, Mendoza.
A10: DEL002 | B10: Bowl de frutas | F10: Bowl de frutas de Amelí Casa de Té & Brunch. | G10: Seasonal Fruit Bowl at Amelí Casa de Té & Brunch. | H10: Bowl de frutas da estação da Amelí Casa de Té & Brunch. | I10: Bol de fruits de saison chez Amelí Casa de Té & Brunch. | J10: Bowl di frutta di stagione da Amelí Casa de Té & Brunch. | K10: bowl-de-frutas | L10: seasonal-fruit-bowl | M10: bowl-de-frutas-da-estacao | N10: bol-de-fruits-de-saison | O10: bowl-di-frutta-di-stagione | P10: Bowl de frutas | Amelí | Q10: Seasonal Fruit Bowl | Amelí | R10: Bowl de frutas da estação | Amelí | S10: Bol de fruits de saison | Amelí | T10: Bowl di frutta di stagione | Amelí | U10: Selección de frutas frescas de estación, servidas en bowl. Disponible en Amelí, Malargüe, Mendoza. | V10: A selection of fresh seasonal fruit, served in a bowl. Available at Amelí in Malargüe, Mendoza. | W10: Seleção de frutas frescas da estação, servidas em bowl. Disponível na Amelí, em Malargüe, Mendoza. | X10: Sélection de fruits frais de saison, servis dans un bol. À découvrir chez Amelí, à Malargüe, Mendoza. | Y10: Selezione di frutta fresca di stagione, servita in bowl. Disponibile da Amelí, a Malargüe, Mendoza.
A11: DEL003 | B11: Chipá | F11: Chipá de Amelí Casa de Té & Brunch. | G11: Chipá Cheese Rolls at Amelí Casa de Té & Brunch. | H11: Pão de queijo tipo chipá da Amelí Casa de Té & Brunch. | I11: Petits pains au fromage chipá chez Amelí Casa de Té & Brunch. | J11: Panini al formaggio chipá da Amelí Casa de Té & Brunch. | K11: chipa | L11: chipa-cheese-rolls | M11: pao-de-queijo-tipo-chipa | N11: petits-pains-au-fromage-chipa | O11: panini-al-formaggio-chipa | P11: Chipá | Amelí | Q11: Chipá Cheese Rolls | Amelí | R11: Pão de queijo tipo chipá | Amelí | S11: Petits pains au fromage chipá | Amelí | T11: Panini al formaggio chipá | Amelí | U11: Panecillos de almidón de mandioca y queso, suaves por dentro y ligeramente crocantes por fuera. Disponible en Amelí, Malargüe, Mendoza. | V11: Cheese rolls made with cassava starch, soft inside and lightly crisp outside. Available at Amelí in Malargüe, Mendoza. | W11: Pãezinhos de polvilho e queijo, macios por dentro e levemente crocantes por fora. Disponível na Amelí, em Malargüe, Mendoza. | X11: Petits pains au fromage à base de fécule de manioc, moelleux à l’intérieur et légèrement croustillants à l’extérieur. À découvrir chez Amelí, à Malargüe… | Y11: Panini al formaggio preparati con amido di manioca, morbidi all’interno e leggermente croccanti fuori. Disponibile da Amelí, a Malargüe, Mendoza.
A12: DEL004 | B12: Medialunas | F12: Medialunas de Amelí Casa de Té & Brunch. | G12: Argentine Croissants at Amelí Casa de Té & Brunch. | H12: Medialunas argentinas da Amelí Casa de Té & Brunch. | I12: Croissants argentins chez Amelí Casa de Té & Brunch. | J12: Cornetti argentini da Amelí Casa de Té & Brunch. | K12: medialunas | L12: argentine-croissants | M12: medialunas-argentinas | N12: croissants-argentins | O12: cornetti-argentini | P12: Medialunas | Amelí | Q12: Argentine Croissants | Amelí | R12: Medialunas argentinas | Amelí | S12: Croissants argentins | Amelí | T12: Cornetti argentini | Amelí | U12: Medialunas argentinas suaves y hojaldradas. Consultar presentación y cantidad por porción. Disponible en Amelí, Malargüe, Mendoza. | V12: Soft, flaky Argentine croissants. Please ask about serving size and presentation. Available at Amelí in Malargüe, Mendoza. | W12: Medialunas argentinas macias e folhadas. Consulte a quantidade e a apresentação da porção. Disponível na Amelí, em Malargüe, Mendoza. | X12: Croissants argentins moelleux et feuilletés. Merci de consulter la quantité et la présentation. À découvrir chez Amelí, à Malargüe, Mendoza. | Y12: Cornetti argentini soffici e sfogliati. Chiedere quantità e presentazione della porzione. Disponibile da Amelí, a Malargüe, Mendoza.
A13: DEL005 | B13: Mini budines | F13: Mini budines de Amelí Casa de Té & Brunch. | G13: Mini Loaf Cakes at Amelí Casa de Té & Brunch. | H13: Mini bolos tipo inglês da Amelí Casa de Té & Brunch. | I13: Mini cakes chez Amelí Casa de Té & Brunch. | J13: Mini plumcake da Amelí Casa de Té & Brunch. | K13: mini-budines | L13: mini-loaf-cakes | M13: mini-bolos-tipo-ingles | N13: mini-cakes | O13: mini-plumcake | P13: Mini budines | Amelí | Q13: Mini Loaf Cakes | Amelí | R13: Mini bolos tipo inglês | Amelí | S13: Mini cakes | Amelí | T13: Mini plumcake | Amelí | U13: Selección de mini budines artesanales. Consultar los sabores disponibles del día. Disponible en Amelí, Malargüe, Mendoza. | V13: A selection of handmade mini loaf cakes. Please ask about today’s available flavours. Available at Amelí in Malargüe, Mendoza. | W13: Seleção de mini bolos artesanais. Consulte os sabores disponíveis do dia. Disponível na Amelí, em Malargüe, Mendoza. | X13: Sélection de mini cakes artisanaux. Merci de demander les parfums disponibles du jour. À découvrir chez Amelí, à Malargüe, Mendoza. | Y13: Selezione di mini plumcake artigianali. Chiedere i gusti disponibili del giorno. Disponibile da Amelí, a Malargüe, Mendoza.
A14: DEL006 | B14: Raspaditas mendocinas | F14: Raspaditas mendocinas de Amelí Casa de Té & Brunch. | G14: Mendoza Raspaditas at Amelí Casa de Té & Brunch. | H14: Raspaditas mendocinas da Amelí Casa de Té & Brunch. | I14: Raspaditas de Mendoza chez Amelí Casa de Té & Brunch. | J14: Raspaditas mendocine da Amelí Casa de Té & Brunch. | K14: raspaditas-mendocinas | L14: mendoza-raspaditas | M14: raspaditas-mendocinas | N14: raspaditas-de-mendoza | O14: raspaditas-mendocine | P14: Raspaditas mendocinas | Amelí | Q14: Mendoza Raspaditas | Amelí | R14: Raspaditas mendocinas | Amelí | S14: Raspaditas de Mendoza | Amelí | T14: Raspaditas mendocine | Amelí | U14: Tortitas saladas tradicionales de Mendoza, de textura firme, ideales para acompañar café, té o mate. Disponible en Amelí, Malargüe, Mendoza. | V14: Traditional savoury baked rounds from Mendoza, with a firm texture and perfect alongside coffee, tea or mate. Available at Amelí in Malargüe, Mendoza. | W14: Tortinhas salgadas tradicionais de Mendoza, de textura firme, ideais para acompanhar café, chá ou mate. Disponível na Amelí, em Malargüe, Mendoza. | X14: Petites galettes salées traditionnelles de Mendoza, à la texture ferme, idéales avec un café, un thé ou du maté. À découvrir chez Amelí, à Malargüe… | Y14: Focaccine salate tradizionali di Mendoza, dalla consistenza compatta, ideali con caffè, tè o mate. Disponibile da Amelí, a Malargüe, Mendoza.
A15: DEL007 | B15: Smoothie bowl | F15: Smoothie bowl de Amelí Casa de Té & Brunch. | G15: Smoothie Bowl at Amelí Casa de Té & Brunch. | H15: Smoothie bowl da Amelí Casa de Té & Brunch. | I15: Smoothie bowl chez Amelí Casa de Té & Brunch. | J15: Smoothie bowl da Amelí Casa de Té & Brunch. | K15: smoothie-bowl | L15: smoothie-bowl | M15: smoothie-bowl | N15: smoothie-bowl | O15: smoothie-bowl | P15: Smoothie bowl | Amelí | Q15: Smoothie Bowl | Amelí | R15: Smoothie bowl | Amelí | S15: Smoothie bowl | Amelí | T15: Smoothie bowl | Amelí | U15: Base cremosa de frutas servida en bowl con toppings. Consultar la combinación disponible del día. Disponible en Amelí, Malargüe, Mendoza. | V15: A creamy fruit base served in a bowl with toppings. Please ask about today’s available combination. Available at Amelí in Malargüe, Mendoza. | W15: Base cremosa de frutas servida em bowl com toppings. Consulte a combinação disponível do dia. Disponível na Amelí, em Malargüe, Mendoza. | X15: Base crémeuse de fruits servie dans un bol avec garnitures. Merci de demander la composition disponible du jour. À découvrir chez Amelí, à Malargüe… | Y15: Base cremosa di frutta servita in bowl con topping. Chiedere la combinazione disponibile del giorno. Disponibile da Amelí, a Malargüe, Mendoza.
A16: TEH001 | B16: Selección de té en hebras | F16: Selección de té en hebras de Amelí Casa de Té & Brunch. | G16: Loose-Leaf Tea Selection at Amelí Casa de Té & Brunch. | H16: Seleção de chás de folhas soltas da Amelí Casa de Té & Brunch. | I16: Sélection de thés en feuilles chez Amelí Casa de Té & Brunch. | J16: Selezione di tè in foglia da Amelí Casa de Té & Brunch. | K16: seleccion-de-te-en-hebras | L16: loose-leaf-tea-selection | M16: selecao-de-chas-de-folhas-soltas | N16: selection-de-thes-en-feuilles | O16: selezione-di-te-in-foglia | P16: Selección de té en hebras | Amelí | Q16: Loose-Leaf Tea Selection | Amelí | R16: Seleção de chás de folhas soltas | Amelí | S16: Sélection de thés en feuilles | Amelí | T16: Selezione di tè in foglia | Amelí | U16: Té negro, pu-erh o verde, preparado en hebras. Disponible en Amelí, Malargüe, Mendoza. | V16: Black, pu-erh or green tea, brewed from loose leaves. Available at Amelí in Malargüe, Mendoza. | W16: Chá preto, pu-erh ou verde, preparado com folhas soltas. Disponível na Amelí, em Malargüe, Mendoza. | X16: Thé noir, pu-erh ou vert, préparé en feuilles. À découvrir chez Amelí, à Malargüe, Mendoza. | Y16: Tè nero, pu-erh o verde, preparato con foglie sfuse. Disponibile da Amelí, a Malargüe, Mendoza.
... A59: SAT005 | B59: Pistachero | F59: Pistachero de Amelí Casa de Té & Brunch. | G59: Pistachio Mortadella Sandwich at Amelí Casa de Té & Brunch. | H59: Sanduíche de mortadela e pistache da Amelí Casa de Té & Brunch. | I59: Sandwich mortadelle & pistache chez Amelí Casa de Té & Brunch. | J59: Panino mortadella & pistacchio da Amelí Casa de Té & Brunch. | K59: pistachero | L59: pistachio-mortadella-sandwich | M59: sanduiche-de-mortadela-e-pistache | N59: sandwich-mortadelle-y-pistache | O59: panino-mortadella-y-pistacchio | P59: Pistachero | Amelí | Q59: Pistachio Mortadella Sandwich | Amelí | R59: Sanduíche de mortadela e pistache | Amelí | S59: Sandwich mortadelle & pistache | Amelí | T59: Panino mortadella & pistacchio | Amelí | U59: Sándwich de mortadela, queso, manteca especiada, pistacho y queso gratinado. Disponible en Amelí, Malargüe, Mendoza. | V59: A sandwich with mortadella, cheese, spiced butter, pistachios and melted cheese. Available at Amelí in Malargüe, Mendoza. | W59: Sanduíche com mortadela, queijo, manteiga temperada, pistache e queijo gratinado. Disponível na Amelí, em Malargüe, Mendoza. | X59: Sandwich à la mortadelle, au fromage, au beurre épicé, aux pistaches et au fromage gratiné. À découvrir chez Amelí, à Malargüe, Mendoza. | Y59: Panino con mortadella, formaggio, burro speziato, pistacchi e formaggio gratinato. Disponibile da Amelí, a Malargüe, Mendoza.

Sheet 11_Canales_QR
A1: Canales, disponibilidad y QR
A2: El QR físico debe ser dinámico y permanente. Las fechas permiten ocultar productos temporales sin cambiar el código impreso.
A4: ID | B4: Producto ES-AR | C4: URL del producto | D4: URL QR | E4: Visible menú QR | F4: Visible web | G4: Visible delivery | H4: Visible Google | I4: Visible Instagram | J4: Visible carta impresa | K4: Disponible desde | L4: Disponible hasta | M4: Estado de publicación | N4: Notas
A5: DYM001 | B5: Avocado | D5: =IF(C5="","",C5) | E5: Sí | F5: Sí | G5: No | H5: No | I5: No | J5: Sí | M5: =IF(02_Productos_MASTER!J5<>"Sí","Ocultar",IF(AND(OR(K5="",TODAY()>=K5),OR(L5="",TODAY()<=L5)),"Publicar","Ocultar")) -> Publicar
A6: DYM002 | B6: Desayuno clásico | D6: =IF(C6="","",C6) | E6: Sí | F6: Sí | G6: No | H6: No | I6: No | J6: Sí | M6: =IF(02_Productos_MASTER!J6<>"Sí","Ocultar",IF(AND(OR(K6="",TODAY()>=K6),OR(L6="",TODAY()<=L6)),"Publicar","Ocultar")) -> Publicar
A7: DYM003 | B7: Desayuno mendocino | D7: =IF(C7="","",C7) | E7: Sí | F7: Sí | G7: No | H7: No | I7: No | J7: Sí | M7: =IF(02_Productos_MASTER!J7<>"Sí","Ocultar",IF(AND(OR(K7="",TODAY()>=K7),OR(L7="",TODAY()<=L7)),"Publicar","Ocultar")) -> Publicar
A8: DYM004 | B8: Desayuno saludable | D8: =IF(C8="","",C8) | E8: Sí | F8: Sí | G8: No | H8: No | I8: No | J8: Sí | M8: =IF(02_Productos_MASTER!J8<>"Sí","Ocultar",IF(AND(OR(K8="",TODAY()>=K8),OR(L8="",TODAY()<=L8)),"Publicar","Ocultar")) -> Publicar
A9: DEL001 | B9: Bowl de huevos | D9: =IF(C9="","",C9) | E9: Sí | F9: Sí | G9: No | H9: No | I9: No | J9: Sí | M9: =IF(02_Productos_MASTER!J9<>"Sí","Ocultar",IF(AND(OR(K9="",TODAY()>=K9),OR(L9="",TODAY()<=L9)),"Publicar","Ocultar")) -> Publicar | N9: Confirmar receta y acompañamientos.
A10: DEL002 | B10: Bowl de frutas | D10: =IF(C10="","",C10) | E10: Sí | F10: Sí | G10: No | H10: No | I10: No | J10: Sí | M10: =IF(02_Productos_MASTER!J10<>"Sí","Ocultar",IF(AND(OR(K10="",TODAY()>=K10),OR(L10="",TODAY()<=L10)),"Publicar","Ocultar")) -> Publicar
A11: DEL003 | B11: Chipá | D11: =IF(C11="","",C11) | E11: Sí | F11: Sí | G11: No | H11: No | I11: No | J11: Sí | M11: =IF(02_Productos_MASTER!J11<>"Sí","Ocultar",IF(AND(OR(K11="",TODAY()>=K11),OR(L11="",TODAY()<=L11)),"Publicar","Ocultar")) -> Publicar
A12: DEL004 | B12: Medialunas | D12: =IF(C12="","",C12) | E12: Sí | F12: Sí | G12: No | H12: No | I12: No | J12: Sí | M12: =IF(02_Productos_MASTER!J12<>"Sí","Ocultar",IF(AND(OR(K12="",TODAY()>=K12),OR(L12="",TODAY()<=L12)),"Publicar","Ocultar")) -> Publicar
A13: DEL005 | B13: Mini budines | D13: =IF(C13="","",C13) | E13: Sí | F13: Sí | G13: No | H13: No | I13: No | J13: Sí | M13: =IF(02_Productos_MASTER!J13<>"Sí","Ocultar",IF(AND(OR(K13="",TODAY()>=K13),OR(L13="",TODAY()<=L13)),"Publicar","Ocultar")) -> Publicar | N13: Los ingredientes varían según el sabor.
A14: DEL006 | B14: Raspaditas mendocinas | D14: =IF(C14="","",C14) | E14: Sí | F14: Sí | G14: No | H14: No | I14: No | J14: Sí | M14: =IF(02_Productos_MASTER!J14<>"Sí","Ocultar",IF(AND(OR(K14="",TODAY()>=K14),OR(L14="",TODAY()<=L14)),"Publicar","Ocultar")) -> Publicar
A15: DEL007 | B15: Smoothie bowl | D15: =IF(C15="","",C15) | E15: Sí | F15: Sí | G15: No | H15: No | I15: No | J15: Sí | M15: =IF(02_Productos_MASTER!J15<>"Sí","Ocultar",IF(AND(OR(K15="",TODAY()>=K15),OR(L15="",TODAY()<=L15)),"Publicar","Ocultar")) -> Publicar | N15: Confirmar ingredientes, toppings y base líquida.
A16: TEH001 | B16: Selección de té en hebras | D16: =IF(C16="","",C16) | E16: Sí | F16: Sí | G16: No | H16: No | I16: No | J16: Sí | M16: =IF(02_Productos_MASTER!J16<>"Sí","Ocultar",IF(AND(OR(K16="",TODAY()>=K16),OR(L16="",TODAY()<=L16)),"Publicar","Ocultar")) -> Publicar
A17: TIS001 | B17: Tisana 1 · Cedrón & lavanda | D17: =IF(C17="","",C17) | E17: Sí | F17: Sí | G17: No | H17: No | I17: No | J17: Sí | M17: =IF(02_Productos_MASTER!J17<>"Sí","Ocultar",IF(AND(OR(K17="",TODAY()>=K17),OR(L17="",TODAY()<=L17)),"Publicar","Ocultar")) -> Publicar
A18: TIS002 | B18: Tisana 2 · Limón & menta | D18: =IF(C18="","",C18) | E18: Sí | F18: Sí | G18: No | H18: No | I18: No | J18: Sí | M18: =IF(02_Productos_MASTER!J18<>"Sí","Ocultar",IF(AND(OR(K18="",TODAY()>=K18),OR(L18="",TODAY()<=L18)),"Publicar","Ocultar")) -> Publicar
A19: TIS003 | B19: Tisana 3 · Manzanilla & melisa | D19: =IF(C19="","",C19) | E19: Sí | F19: Sí | G19: No | H19: No | I19: No | J19: Sí | M19: =IF(02_Productos_MASTER!J19<>"Sí","Ocultar",IF(AND(OR(K19="",TODAY()>=K19),OR(L19="",TODAY()<=L19)),"Publicar","Ocultar")) -> Publicar
A20: BLE001 | B20: Del bosque | D20: =IF(C20="","",C20) | E20: Sí | F20: Sí | G20: No | H20: No | I20: No | J20: Sí | M20: =IF(02_Productos_MASTER!J20<>"Sí","Ocultar",IF(AND(OR(K20="",TODAY()>=K20),OR(L20="",TODAY()<=L20)),"Publicar","Ocultar")) -> Publicar
A21: BLE002 | B21: Detox | D21: =IF(C21="","",C21) | E21: Sí | F21: Sí | G21: No | H21: No | I21: No | J21: Sí | M21: =IF(02_Productos_MASTER!J21<>"Sí","Ocultar",IF(AND(OR(K21="",TODAY()>=K21),OR(L21="",TODAY()<=L21)),"Publicar","Ocultar")) -> Publicar
A22: BLE003 | B22: Dorado | D22: =IF(C22="","",C22) | E22: Sí | F22: Sí | G22: No | H22: No | I22: No | J22: Sí | M22: =IF(02_Productos_MASTER!J22<>"Sí","Ocultar",IF(AND(OR(K22="",TODAY()>=K22),OR(L22="",TODAY()<=L22)),"Publicar","Ocultar")) -> Publicar
A23: BLE004 | B23: Love | D23: =IF(C23="","",C23) | E23: Sí | F23: Sí | G23: No | H23: No | I23: No | J23: Sí | M23: =IF(02_Productos_MASTER!J23<>"Sí","Ocultar",IF(AND(OR(K23="",TODAY()>=K23),OR(L23="",TODAY()<=L23)),"Publicar","Ocultar")) -> Publicar
A24: ESP001 | B24: Submarino | D24: =IF(C24="","",C24) | E24: Sí | F24: Sí | G24: No | H24: No | I24: No | J24: Sí | M24: =IF(02_Productos_MASTER!J24<>"Sí","Ocultar",IF(AND(OR(K24="",TODAY()>=K24),OR(L24="",TODAY()<=L24)),"Publicar","Ocultar")) -> Publicar
A25: ESP002 | B25: Leche dorada | D25: =IF(C25="","",C25) | E25: Sí | F25: Sí | G25: No | H25: No | I25: No | J25: Sí | M25: =IF(02_Productos_MASTER!J25<>"Sí","Ocultar",IF(AND(OR(K25="",TODAY()>=K25),OR(L25="",TODAY()<=L25)),"Publicar","Ocultar")) -> Publicar
A26: CCL001 | B26: Americano | D26: =IF(C26="","",C26) | E26: Sí | F26: Sí | G26: No | H26: No | I26: No | J26: Sí | M26: =IF(02_Productos_MASTER!J26<>"Sí","Ocultar",IF(AND(OR(K26="",TODAY()>=K26),OR(L26="",TODAY()<=L26)),"Publicar","Ocultar")) -> Publicar
A27: CCL002 | B27: Cortado | D27: =IF(C27="","",C27) | E27: Sí | F27: Sí | G27: No | H27: No | I27: No | J27: Sí | M27: =IF(02_Productos_MASTER!J27<>"Sí","Ocultar",IF(AND(OR(K27="",TODAY()>=K27),OR(L27="",TODAY()<=L27)),"Publicar","Ocultar")) -> Publicar
... A35: CFR003 | B35: Frappé de dulce de leche | D35: =IF(C35="","",C35) | E35: Sí | F35: Sí | G35: No | H35: No | I35: No | J35: Sí | M35: =IF(02_Productos_MASTER!J35<>"Sí","Ocultar",IF(AND(OR(K35="",TODAY()>=K35),OR(L35="",TODAY()<=L35)),"Publicar","Ocultar")) -> Publicar
A36: BYJ001 | B36: Batido de banana | D36: =IF(C36="","",C36) | E36: Sí | F36: Sí | G36: No | H36: No | I36: No | J36: Sí | M36: =IF(02_Productos_MASTER!J36<>"Sí","Ocultar",IF(AND(OR(K36="",TODAY()>=K36),OR(L36="",TODAY()<=L36)),"Publicar","Ocultar")) -> Publicar | N36: Confirmar si la base contiene leche.
A37: BYJ002 | B37: Batido de frutos rojos | D37: =IF(C37="","",C37) | E37: Sí | F37: Sí | G37: No | H37: No | I37: No | J37: Sí | M37: =IF(02_Productos_MASTER!J37<>"Sí","Ocultar",IF(AND(OR(K37="",TODAY()>=K37),OR(L37="",TODAY()<=L37)),"Publicar","Ocultar")) -> Publicar
A38: BYJ003 | B38: Limonada detox | D38: =IF(C38="","",C38) | E38: Sí | F38: Sí | G38: No | H38: No | I38: No | J38: Sí | M38: =IF(02_Productos_MASTER!J38<>"Sí","Ocultar",IF(AND(OR(K38="",TODAY()>=K38),OR(L38="",TODAY()<=L38)),"Publicar","Ocultar")) -> Publicar
A39: BYJ004 | B39: Limonada Jamaica | D39: =IF(C39="","",C39) | E39: Sí | F39: Sí | G39: No | H39: No | I39: No | J39: Sí | M39: =IF(02_Productos_MASTER!J39<>"Sí","Ocultar",IF(AND(OR(K39="",TODAY()>=K39),OR(L39="",TODAY()<=L39)),"Publicar","Ocultar")) -> Publicar
A40: BYJ005 | B40: Jugo de naranja | D40: =IF(C40="","",C40) | E40: Sí | F40: Sí | G40: No | H40: No | I40: No | J40: Sí | M40: =IF(02_Productos_MASTER!J40<>"Sí","Ocultar",IF(AND(OR(K40="",TODAY()>=K40),OR(L40="",TODAY()<=L40)),"Publicar","Ocultar")) -> Publicar
A41: BYJ006 | B41: Tropical | D41: =IF(C41="","",C41) | E41: Sí | F41: Sí | G41: No | H41: No | I41: No | J41: Sí | M41: =IF(02_Productos_MASTER!J41<>"Sí","Ocultar",IF(AND(OR(K41="",TODAY()>=K41),OR(L41="",TODAY()<=L41)),"Publicar","Ocultar")) -> Publicar
A42: ADI001 | B42: Leche vegetal | D42: =IF(C42="","",C42) | E42: Sí | F42: Sí | G42: No | H42: No | I42: No | J42: Sí | M42: =IF(02_Productos_MASTER!J42<>"Sí","Ocultar",IF(AND(OR(K42="",TODAY()>=K42),OR(L42="",TODAY()<=L42)),"Publicar","Ocultar")) -> Publicar
A43: ADI002 | B43: Leche sin lactosa | D43: =IF(C43="","",C43) | E43: Sí | F43: Sí | G43: No | H43: No | I43: No | J43: Sí | M43: =IF(02_Productos_MASTER!J43<>"Sí","Ocultar",IF(AND(OR(K43="",TODAY()>=K43),OR(L43="",TODAY()<=L43)),"Publicar","Ocultar")) -> Publicar
A44: STC001 | B44: Postres sin TACC | D44: =IF(C44="","",C44) | E44: Sí | F44: Sí | G44: No | H44: No | I44: No | J44: Sí | M44: =IF(02_Productos_MASTER!J44<>"Sí","Ocultar",IF(AND(OR(K44="",TODAY()>=K44),OR(L44="",TODAY()<=L44)),"Publicar","Ocultar")) -> Publicar | N44: Validar certificación, proveedor y riesgo de contaminación cruzada.
A45: STC002 | B45: Pasta frola sin TACC | D45: =IF(C45="","",C45) | E45: Sí | F45: Sí | G45: No | H45: No | I45: No | J45: Sí | M45: =IF(02_Productos_MASTER!J45<>"Sí","Ocultar",IF(AND(OR(K45="",TODAY()>=K45),OR(L45="",TODAY()<=L45)),"Publicar","Ocultar")) -> Publicar | N45: Validar certificación, proveedor y riesgo de contaminación cruzada.
A46: STC003 | B46: Tarta de coco y dulce de leche sin TACC | D46: =IF(C46="","",C46) | E46: Sí | F46: Sí | G46: No | H46: No | I46: No | J46: Sí | M46: =IF(02_Productos_MASTER!J46<>"Sí","Ocultar",IF(AND(OR(K46="",TODAY()>=K46),OR(L46="",TODAY()<=L46)),"Publicar","Ocultar")) -> Publicar | N46: Validar certificación, proveedor y riesgo de contaminación cruzada.
A47: STC004 | B47: Alfacookie sin TACC | D47: =IF(C47="","",C47) | E47: Sí | F47: Sí | G47: No | H47: No | I47: No | J47: Sí | M47: =IF(02_Productos_MASTER!J47<>"Sí","Ocultar",IF(AND(OR(K47="",TODAY()>=K47),OR(L47="",TODAY()<=L47)),"Publicar","Ocultar")) -> Publicar | N47: Validar certificación, proveedor y riesgo de contaminación cruzada.
A48: TYT001 | B48: Torta Amelí | D48: =IF(C48="","",C48) | E48: Sí | F48: Sí | G48: No | H48: No | I48: No | J48: Sí | M48: =IF(02_Productos_MASTER!J48<>"Sí","Ocultar",IF(AND(OR(K48="",TODAY()>=K48),OR(L48="",TODAY()<=L48)),"Publicar","Ocultar")) -> Publicar
A49: TYT002 | B49: Marquise | D49: =IF(C49="","",C49) | E49: Sí | F49: Sí | G49: No | H49: No | I49: No | J49: Sí | M49: =IF(02_Productos_MASTER!J49<>"Sí","Ocultar",IF(AND(OR(K49="",TODAY()>=K49),OR(L49="",TODAY()<=L49)),"Publicar","Ocultar")) -> Publicar
A50: TYT003 | B50: Cheesecake de frutos rojos | D50: =IF(C50="","",C50) | E50: Sí | F50: Sí | G50: No | H50: No | I50: No | J50: Sí | M50: =IF(02_Productos_MASTER!J50<>"Sí","Ocultar",IF(AND(OR(K50="",TODAY()>=K50),OR(L50="",TODAY()<=L50)),"Publicar","Ocultar")) -> Publicar
A51: TYT004 | B51: Red velvet | D51: =IF(C51="","",C51) | E51: Sí | F51: Sí | G51: No | H51: No | I51: No | J51: Sí | M51: =IF(02_Productos_MASTER!J51<>"Sí","Ocultar",IF(AND(OR(K51="",TODAY()>=K51),OR(L51="",TODAY()<=L51)),"Publicar","Ocultar")) -> Publicar
A52: TYT005 | B52: Key lime pie | D52: =IF(C52="","",C52) | E52: Sí | F52: Sí | G52: No | H52: No | I52: No | J52: Sí | M52: =IF(02_Productos_MASTER!J52<>"Sí","Ocultar",IF(AND(OR(K52="",TODAY()>=K52),OR(L52="",TODAY()<=L52)),"Publicar","Ocultar")) -> Publicar
A53: TYT006 | B53: Sablée de almendras | D53: =IF(C53="","",C53) | E53: Sí | F53: Sí | G53: No | H53: No | I53: No | J53: Sí | M53: =IF(02_Productos_MASTER!J53<>"Sí","Ocultar",IF(AND(OR(K53="",TODAY()>=K53),OR(L53="",TODAY()<=L53)),"Publicar","Ocultar")) -> Publicar
A54: TYT007 | B54: Franuí del bosque | D54: =IF(C54="","",C54) | E54: Sí | F54: Sí | G54: No | H54: No | I54: No | J54: Sí | M54: =IF(02_Productos_MASTER!J54<>"Sí","Ocultar",IF(AND(OR(K54="",TODAY()>=K54),OR(L54="",TODAY()<=L54)),"Publicar","Ocultar")) -> Publicar
A55: SAT001 | B55: Bagel | D55: =IF(C55="","",C55) | E55: Sí | F55: Sí | G55: No | H55: No | I55: No | J55: Sí | M55: =IF(02_Productos_MASTER!J55<>"Sí","Ocultar",IF(AND(OR(K55="",TODAY()>=K55),OR(L55="",TODAY()<=L55)),"Publicar","Ocultar")) -> Publicar
A56: SAT002 | B56: Tostado de jamón y queso | D56: =IF(C56="","",C56) | E56: Sí | F56: Sí | G56: No | H56: No | I56: No | J56: Sí | M56: =IF(02_Productos_MASTER!J56<>"Sí","Ocultar",IF(AND(OR(K56="",TODAY()>=K56),OR(L56="",TODAY()<=L56)),"Publicar","Ocultar")) -> Publicar
A57: SAT003 | B57: Tostón Amelí | D57: =IF(C57="","",C57) | E57: Sí | F57: Sí | G57: No | H57: No | I57: No | J57: Sí | M57: =IF(02_Productos_MASTER!J57<>"Sí","Ocultar",IF(AND(OR(K57="",TODAY()>=K57),OR(L57="",TODAY()<=L57)),"Publicar","Ocultar")) -> Publicar
A58: SAT004 | B58: Tostón de palta y huevo | D58: =IF(C58="","",C58) | E58: Sí | F58: Sí | G58: No | H58: No | I58: No | J58: Sí | M58: =IF(02_Productos_MASTER!J58<>"Sí","Ocultar",IF(AND(OR(K58="",TODAY()>=K58),OR(L58="",TODAY()<=L58)),"Publicar","Ocultar")) -> Publicar
A59: SAT005 | B59: Pistachero | D59: =IF(C59="","",C59) | E59: Sí | F59: Sí | G59: No | H59: No | I59: No | J59: Sí | M59: =IF(02_Productos_MASTER!J59<>"Sí","Ocultar",IF(AND(OR(K59="",TODAY()>=K59),OR(L59="",TODAY()<=L59)),"Publicar","Ocultar")) -> Publicar

Sheet 12_Estadísticas
A1: Estadísticas del menú digital
A2: Cargar datos por período. Los ingresos, el CTR y la conversión se calculan automáticamente.
A4: ID | B4: Producto ES-AR | C4: Unidades vendidas | D4: Última venta | E4: Valoración | F4: Cantidad de reseñas | G4: Favoritos | H4: Escaneos QR | I4: Clics en producto | J4: Pedidos atribuidos | K4: Ingresos estimados | L4: CTR producto | M4: Conversión | N4: Periodo desde | O4: Periodo hasta | P4: Observaciones
A5: DYM001 | B5: Avocado | K5: =IF(C5="","",IFERROR(C5*INDEX(04_Precios!$D$5:$D$59,MATCH($A5,04_Precios!$A$5:$A$59,0)),"")) | L5: =IFERROR(I5/H5,"") | M5: =IFERROR(J5/I5,"")
A6: DYM002 | B6: Desayuno clásico | K6: =IF(C6="","",IFERROR(C6*INDEX(04_Precios!$D$5:$D$59,MATCH($A6,04_Precios!$A$5:$A$59,0)),"")) | L6: =IFERROR(I6/H6,"") | M6: =IFERROR(J6/I6,"")
A7: DYM003 | B7: Desayuno mendocino | K7: =IF(C7="","",IFERROR(C7*INDEX(04_Precios!$D$5:$D$59,MATCH($A7,04_Precios!$A$5:$A$59,0)),"")) | L7: =IFERROR(I7/H7,"") | M7: =IFERROR(J7/I7,"")
A8: DYM004 | B8: Desayuno saludable | K8: =IF(C8="","",IFERROR(C8*INDEX(04_Precios!$D$5:$D$59,MATCH($A8,04_Precios!$A$5:$A$59,0)),"")) | L8: =IFERROR(I8/H8,"") | M8: =IFERROR(J8/I8,"")
A9: DEL001 | B9: Bowl de huevos | K9: =IF(C9="","",IFERROR(C9*INDEX(04_Precios!$D$5:$D$59,MATCH($A9,04_Precios!$A$5:$A$59,0)),"")) | L9: =IFERROR(I9/H9,"") | M9: =IFERROR(J9/I9,"")
A10: DEL002 | B10: Bowl de frutas | K10: =IF(C10="","",IFERROR(C10*INDEX(04_Precios!$D$5:$D$59,MATCH($A10,04_Precios!$A$5:$A$59,0)),"")) | L10: =IFERROR(I10/H10,"") | M10: =IFERROR(J10/I10,"")
A11: DEL003 | B11: Chipá | K11: =IF(C11="","",IFERROR(C11*INDEX(04_Precios!$D$5:$D$59,MATCH($A11,04_Precios!$A$5:$A$59,0)),"")) | L11: =IFERROR(I11/H11,"") | M11: =IFERROR(J11/I11,"")
A12: DEL004 | B12: Medialunas | K12: =IF(C12="","",IFERROR(C12*INDEX(04_Precios!$D$5:$D$59,MATCH($A12,04_Precios!$A$5:$A$59,0)),"")) | L12: =IFERROR(I12/H12,"") | M12: =IFERROR(J12/I12,"")
A13: DEL005 | B13: Mini budines | K13: =IF(C13="","",IFERROR(C13*INDEX(04_Precios!$D$5:$D$59,MATCH($A13,04_Precios!$A$5:$A$59,0)),"")) | L13: =IFERROR(I13/H13,"") | M13: =IFERROR(J13/I13,"")
A14: DEL006 | B14: Raspaditas mendocinas | K14: =IF(C14="","",IFERROR(C14*INDEX(04_Precios!$D$5:$D$59,MATCH($A14,04_Precios!$A$5:$A$59,0)),"")) | L14: =IFERROR(I14/H14,"") | M14: =IFERROR(J14/I14,"")
A15: DEL007 | B15: Smoothie bowl | K15: =IF(C15="","",IFERROR(C15*INDEX(04_Precios!$D$5:$D$59,MATCH($A15,04_Precios!$A$5:$A$59,0)),"")) | L15: =IFERROR(I15/H15,"") | M15: =IFERROR(J15/I15,"")
A16: TEH001 | B16: Selección de té en hebras | K16: =IF(C16="","",IFERROR(C16*INDEX(04_Precios!$D$5:$D$59,MATCH($A16,04_Precios!$A$5:$A$59,0)),"")) | L16: =IFERROR(I16/H16,"") | M16: =IFERROR(J16/I16,"")
... A59: SAT005 | B59: Pistachero | K59: =IF(C59="","",IFERROR(C59*INDEX(04_Precios!$D$5:$D$59,MATCH($A59,04_Precios!$A$5:$A$59,0)),"")) | L59: =IFERROR(I59/H59,"") | M59: =IFERROR(J59/I59,"")

Sheet 13_Configuración
A1: Configuración general · Menú digital Amelí
A2: Celdas crema = completar o revisar. No publicar alérgenos ni afirmaciones «Sin TACC» sin validar recetas, etiquetas, proveedor y manipulación.
A4: Parámetro | B4: Valor | C4: Uso | E4: Lista | F4: Valores permitidos
A5: Moneda local | B5: ARS | C5: Precios del local | E5: Sí / No | F5: Sí | No
A6: Tipo de cambio ARS/USD | C6: Completar manualmente para calcular precios de referencia en USD | E6: Sí / No / Verificar | F6: Sí | No | Verificar
A7: IVA incluido por defecto | B7: Sí | C7: Control informativo | E7: Estado | F7: Activo | Inactivo | Temporal
A8: Fecha de actualización | B8: =TODAY() -> 46219 | C8: Se calcula automáticamente | E8: Moneda | F8: ARS | USD
A9: Tipo de QR recomendado | B9: Dinámico | C9: Permite cambiar la URL sin reimprimir el código | E9: Clasificación | F9: Estrella | Caballo de batalla | Puzzle | Perro | Sin datos
A10: Duración de sesión sugerida (minutos) | B10: 180 | C10: Para la sesión web; el QR físico no debería expirar | E10: Temperatura | F10: Caliente | Fría | Ambiente | Mixta | Según bebida
A11: URL base del menú | C11: Ejemplo: https://menu.ameli.com.ar | E11: Tipo de QR | F11: Dinámico | Estático
A12: WhatsApp de pedidos | C12: Formato internacional, sin espacios
A13: Instagram | B13: @ameli | C13: Actualizar con el usuario definitivo
A14: Dirección | B14: Malargüe, Mendoza, Argentina | C14: Completar dirección exacta

Sheet 99_Listas
A1: Listas técnicas para los desplegables. Esta hoja está oculta: no hace falta tocarla.
A2: SiNo | B2: SNV | C2: Temperatura | D2: Clasif
A3: Sí | B3: Sí | C3: Caliente | D3: Estrella
A4: No | B4: No | C4: Fría | D4: Caballo de batalla
B5: Verificar | C5: Ambiente | D5: Incógnita
C6: Mixta | D6: Perro
C7: Caliente/Ambiente | D7: Sin datos
C8: Fría/Ambiente
C9: Según bebida
